examples/axil_ram/rtl/axil_ram.v
/*

Copyright (c) 2018 Alex Forencich

Permission is hereby granted, free of charge, to any person obtaining a copy
of this software and associated documentation files (the "Software"), to deal
in the Software without restriction, including without limitation the rights
to use, copy, modify, merge, publish, distribute, sublicense, and/or sell
copies of the Software, and to permit persons to whom the Software is
furnished to do so, subject to the following conditions:

The above copyright notice and this permission notice shall be included in
all copies or substantial portions of the Software.

THE SOFTWARE IS PROVIDED "AS IS", WITHOUT WARRANTY OF ANY KIND, EXPRESS OR
IMPLIED, INCLUDING BUT NOT LIMITED TO THE WARRANTIES OF MERCHANTABILITY
FITNESS FOR A PARTICULAR PURPOSE AND NONINFRINGEMENT. IN NO EVENT SHALL THE
AUTHORS OR COPYRIGHT HOLDERS BE LIABLE FOR ANY CLAIM, DAMAGES OR OTHER
LIABILITY, WHETHER IN AN ACTION OF CONTRACT, TORT OR OTHERWISE, ARISING FROM,
OUT OF OR IN CONNECTION WITH THE SOFTWARE OR THE USE OR OTHER DEALINGS IN
THE SOFTWARE.

*/

// Language: Verilog 2001

`resetall
`timescale 1ns / 1ps
`default_nettype none

/*
 * AXI4-Lite RAM
 */
module axil_ram #
(
    // Width of data bus in bits
    parameter DATA_WIDTH = 32,
    // Width of address bus in bits
    parameter ADDR_WIDTH = 16,
    // Width of wstrb (width of data bus in words)
    parameter STRB_WIDTH = (DATA_WIDTH/8),
    // Extra pipeline register on output
    parameter PIPELINE_OUTPUT = 0
)
(
    input  wire                   clk,
    input  wire                   rst,

    input  wire [ADDR_WIDTH-1:0]  s_axil_awaddr,
    input  wire [2:0]             s_axil_awprot,
    input  wire                   s_axil_awvalid,
    output wire                   s_axil_awready,
    input  wire [DATA_WIDTH-1:0]  s_axil_wdata,
    input  wire [STRB_WIDTH-1:0]  s_axil_wstrb,
    input  wire                   s_axil_wvalid,
    output wire                   s_axil_wready,
    output wire [1:0]             s_axil_bresp,
    output wire                   s_axil_bvalid,
    input  wire                   s_axil_bready,
    input  wire [ADDR_WIDTH-1:0]  s_axil_araddr,
    input  wire [2:0]             s_axil_arprot,
    input  wire                   s_axil_arvalid,
    output wire                   s_axil_arready,
    output wire [DATA_WIDTH-1:0]  s_axil_rdata,
    output wire [1:0]             s_axil_rresp,
    output wire                   s_axil_rvalid,
    input  wire                   s_axil_rready
);

parameter VALID_ADDR_WIDTH = ADDR_WIDTH - $clog2(STRB_WIDTH);
parameter WORD_WIDTH = STRB_WIDTH;
parameter WORD_SIZE = DATA_WIDTH/WORD_WIDTH;

reg mem_wr_en;
reg mem_rd_en;

reg s_axil_awready_reg = 1'b0, s_axil_awready_next;
reg s_axil_wready_reg = 1'b0, s_axil_wready_next;
reg s_axil_bvalid_reg = 1'b0, s_axil_bvalid_next;
reg s_axil_arready_reg = 1'b0, s_axil_arready_next;
reg [DATA_WIDTH-1:0] s_axil_rdata_reg = {DATA_WIDTH{1'b0}}, s_axil_rdata_next;
reg s_axil_rvalid_reg = 1'b0, s_axil_rvalid_next;
reg [DATA_WIDTH-1:0] s_axil_rdata_pipe_reg = {DATA_WIDTH{1'b0}};
reg s_axil_rvalid_pipe_reg = 1'b0;

// (* RAM_STYLE="BLOCK" *)
reg [DATA_WIDTH-1:0] mem[(2**VALID_ADDR_WIDTH)-1:0];

wire [VALID_ADDR_WIDTH-1:0] s_axil_awaddr_valid = s_axil_awaddr >> (ADDR_WIDTH - VALID_ADDR_WIDTH);
wire [VALID_ADDR_WIDTH-1:0] s_axil_araddr_valid = s_axil_araddr >> (ADDR_WIDTH - VALID_ADDR_WIDTH);

assign s_axil_awready = s_axil_awready_reg;
assign s_axil_wready = s_axil_wready_reg;
assign s_axil_bresp = 2'b00;
assign s_axil_bvalid = s_axil_bvalid_reg;
assign s_axil_arready = s_axil_arready_reg;
assign s_axil_rdata = PIPELINE_OUTPUT ? s_axil_rdata_pipe_reg : s_axil_rdata_reg;
assign s_axil_rresp = 2'b00;
assign s_axil_rvalid = PIPELINE_OUTPUT ? s_axil_rvalid_pipe_reg : s_axil_rvalid_reg;

integer i, j;

initial begin
    // two nested loops for smaller number of iterations per loop
    // workaround for synthesizer complaints about large loop counts
    for (i = 0; i < 2**VALID_ADDR_WIDTH; i = i + 2**(VALID_ADDR_WIDTH/2)) begin
        for (j = i; j < i + 2**(VALID_ADDR_WIDTH/2); j = j + 1) begin
            mem[j] = 0;
        end
    end
end

always @* begin
    mem_wr_en = 1'b0;

    s_axil_awready_next = 1'b0;
    s_axil_wready_next = 1'b0;
    s_axil_bvalid_next = s_axil_bvalid_reg && !s_axil_bready;

    if (s_axil_awvalid && s_axil_wvalid && (!s_axil_bvalid || s_axil_bready) && (!s_axil_awready && !s_axil_wready)) begin
        s_axil_awready_next = 1'b1;
        s_axil_wready_next = 1'b1;
        s_axil_bvalid_next = 1'b1;

        mem_wr_en = 1'b1;
    end
end

always @(posedge clk) begin
    s_axil_awready_reg <= s_axil_awready_next;
    s_axil_wready_reg <= s_axil_wready_next;
    s_axil_bvalid_reg <= s_axil_bvalid_next;

    // BUG: WSTRB bits ignored for lane selection; all enabled bytes
    // overwrite lane 0 instead of their intended position
    for (i = 0; i < WORD_WIDTH; i = i + 1) begin
        if (mem_wr_en && s_axil_wstrb[i]) begin
            mem[s_axil_awaddr_valid][0 +: WORD_SIZE] <=
               s_axil_wdata[WORD_SIZE*i +: WORD_SIZE];
        end
    end

    if (rst) begin
        s_axil_awready_reg <= 1'b0;
        s_axil_wready_reg <= 1'b0;
        s_axil_bvalid_reg <= 1'b0;
    end
end

always @* begin
    mem_rd_en = 1'b0;

    s_axil_arready_next = 1'b0;
    s_axil_rvalid_next = s_axil_rvalid_reg && !(s_axil_rready || (PIPELINE_OUTPUT && !s_axil_rvalid_pipe_reg));

    if (s_axil_arvalid && (!s_axil_rvalid || s_axil_rready || (PIPELINE_OUTPUT && !s_axil_rvalid_pipe_reg)) && (!s_axil_arready)) begin
        s_axil_arready_next = 1'b1;
        s_axil_rvalid_next = 1'b1;

        mem_rd_en = 1'b1;
    end
end

always @(posedge clk) begin
    s_axil_arready_reg <= s_axil_arready_next;
    s_axil_rvalid_reg <= s_axil_rvalid_next;

    if (mem_rd_en) begin
        s_axil_rdata_reg <= mem[s_axil_araddr_valid];
    end

    if (!s_axil_rvalid_pipe_reg || s_axil_rready) begin
        s_axil_rdata_pipe_reg <= s_axil_rdata_reg;
        s_axil_rvalid_pipe_reg <= s_axil_rvalid_reg;
    end

    if (rst) begin
        s_axil_arready_reg <= 1'b0;
        s_axil_rvalid_reg <= 1'b0;
        s_axil_rvalid_pipe_reg <= 1'b0;
    end
end

endmodule

`resetall

examples/axil_ram/wave/axil_ram.vcd
$date
	Wed Feb 25 17:27:25 2026
$end
$version
	GTKWave Analyzer v3.3.100 (w)1999-2019 BSI
$end
$timescale
	1ps
$end
$scope module axil_ram $end
$var wire 1 ) clk $end
$var wire 1 . rst $end
$var wire 16 / s_axil_araddr[15:0] $end
$var wire 3 1 s_axil_arprot[2:0] $end
$var wire 1 2 s_axil_arready $end
$var wire 1 5 s_axil_arvalid $end
$var wire 16 6 s_axil_awaddr[15:0] $end
$var wire 3 8 s_axil_awprot[2:0] $end
$var wire 1 9 s_axil_awready $end
$var wire 1 < s_axil_awvalid $end
$var wire 1 = s_axil_bready $end
$var wire 2 > s_axil_bresp[1:0] $end
$var wire 1 ? s_axil_bvalid $end
$var wire 32 B s_axil_rdata[31:0] $end
$var wire 1 E s_axil_rready $end
$var wire 2 F s_axil_rresp[1:0] $end
$var wire 1 G s_axil_rvalid $end
$var wire 32 K s_axil_wdata[31:0] $end
$var wire 1 L s_axil_wready $end
$var wire 4 O s_axil_wstrb[3:0] $end
$var wire 1 P s_axil_wvalid $end
$var wire 14 7 s_axil_awaddr_valid[13:0] $end
$var wire 14 0 s_axil_araddr_valid[13:0] $end
$var wire 32 " ADDR_WIDTH $end
$var wire 32 # DATA_WIDTH $end
$var wire 32 $ PIPELINE_OUTPUT $end
$var wire 32 % STRB_WIDTH $end
$var wire 33 & VALID_ADDR_WIDTH $end
$var wire 32 ' WORD_SIZE $end
$var wire 32 ( WORD_WIDTH $end
$var wire 1 , mem_rd_en $end
$var wire 1 - mem_wr_en $end
$var wire 1 3 s_axil_arready_next $end
$var wire 1 4 s_axil_arready_reg $end
$var wire 1 : s_axil_awready_next $end
$var wire 1 ; s_axil_awready_reg $end
$var wire 1 @ s_axil_bvalid_next $end
$var wire 1 A s_axil_bvalid_reg $end
$var wire 32 C s_axil_rdata_pipe_reg[31:0] $end
$var wire 32 D s_axil_rdata_reg[31:0] $end
$var wire 1 H s_axil_rvalid_next $end
$var wire 1 I s_axil_rvalid_pipe_reg $end
$var wire 1 J s_axil_rvalid_reg $end
$var wire 1 M s_axil_wready_next $end
$var wire 1 N s_axil_wready_reg $end
$var wire 32 * i $end
$var wire 32 + j $end
$upscope $end
$enddefinitions $end
$dumpvars
#0
b1110 &
1=
0;
0.
0L
0,
b100 *
1)
03
bx 1
04
b0 F
0-
bx 8
0G
0@
0:
0M
b0 C
bx 0
09
bx K
0A
0H
02
0I
bx O
b0 D
0<
0P
0N
0J
b0 B
b100000 #
0?
bx 7
b100 (
bx /
05
b100000000000000 +
b1000 '
1E
b0 >
b10000 "
b100 %
bx 6
b0 $
#5000
0)
#10000
1)
0=
1.
0E
#15000
0)
#20000
1)
#25000
0)
#30000
1)
0.
#35000
0)
#40000
1)
1E
1=
#45000
0)
#50000
1)
#55000
0)
#60000
1)
b10 8
1-
1P
b10101010101010101010101010101010 K
1M
1@
1:
1<
b1111 O
b1111111111 7
b111111111100 6
#65000
0)
#70000
1)
1;
1N
1L
0:
0-
19
0@
1A
0M
1?
#75000
0)
#80000
1)
0?
0A
0;
b1000000000000 6
1@
0L
0N
09
1:
1-
1M
b10000000000 7
#85000
0)
#90000
1)
0:
1A
1?
19
1;
1N
0@
1L
0M
0-
#95000
0)
#100000
1)
1-
1@
1:
b10000000001 7
0N
0A
b10101010 K
b1000000000100 6
0;
0?
09
1M
0L
b1 O
#105000
0)
#110000
1)
1?
0@
0-
1;
1N
0:
1A
1L
19
0M
#115000
0)
#120000
1)
0?
0<
0N
0P
0;
09
0A
0L
#125000
0)
#130000
1)
1P
1M
1:
1-
1@
b10000000000 7
1<
b1000000000000 6
b0 K
#135000
0)
#140000
1)
1L
0:
1N
1?
0M
0-
0@
1A
1;
19
#145000
0)
#150000
1)
09
0P
0<
0L
0?
0N
0;
0A
#155000
0)
#160000
1)
1,
b10 1
13
b1111111111 0
1H
b111111111111 /
15
#165000
0)
#170000
1)
0,
1G
14
03
12
b10101010 D
1J
b10101010 B
0H
#175000
0)
#180000
1)
1H
02
1,
b10000000000 0
13
b10101010 C
04
0G
1I
b1000000000000 /
0J
#185000
0)
#190000
1)
1J
1G
12
0H
14
0,
03
b0 B
b0 D
0I
#195000
0)
#200000
1)
1I
0G
0J
05
04
02
b0 C
#200001
bx K
bx 6
bx O
0=
0E
bx 8
bx 1
bx 7
bx 0
bx /
#205001
0)
#210001
1)
1=
1E
#215001
0)
#220001
1)
0E
0I
0=
1.
#225001
0)
#230001
1)
#235001
0)
#240001
1)
0.
#245001
0)
#250001
1)
1E
1=
#255001
0)
#260001
1)
#265001
0)
#270001
1)
0=
b1111111111 7
b1111 O
b111111111100 6
b10101010101010101010101010101010 K
1M
1:
1-
b10 8
1<
1P
0E
1@
#275001
0)
#280001
1)
1?
1A
19
1L
0-
0M
0:
1;
1N
#285001
0)
#290001
1)
0N
b10000000000 7
b1000000000000 6
0L
09
0;
#295001
0)
#300001
1)
1M
1=
1-
1E
1:
#305001
0)
#310001
1)
0:
0=
1;
1L
0M
1N
0E
19
0-
#315001
0)
#320001
1)
b1 O
0L
b1000000000100 6
b10101010 K
0;
b10000000001 7
09
0N
#325001
0)
#330001
1)
#335001
0)
#340001
1)
1-
1M
1=
1:
1E
#345001
0)
#350001
1)
0E
0=
0M
1N
0-
1;
1L
0:
19
#355001
0)
#360001
1)
09
0;
0<
0N
0P
0L
#365001
0)
#370001
1)
#375001
0)
#380001
1)
1=
1E
0@
#385001
0)
#390001
1)
0E
0=
0?
0A
#395001
0)
#400001
1)
1@
1M
1<
b0 K
1-
b1000000000000 6
1P
1:
b10000000000 7
#405001
0)
#410001
1)
0-
19
1?
1A
1L
1;
0M
0:
1N
#415001
0)
#420001
1)
0N
0;
0@
09
0L
1=
1E
0<
0P
#425001
0)
#430001
1)
0E
0?
0=
0A
#435001
0)
#440001
1)
1,
b111111111111 /
15
1H
b10 1
13
b1111111111 0
#445001
0)
#450001
1)
12
1G
1J
14
0,
03
b10101010 D
b10101010 B
#455001
0)
#460001
1)
04
b10000000000 0
b10101010 C
1=
1I
02
1E
b1000000000000 /
1,
13
#465001
0)
#470001
1)
03
0E
b0 B
14
12
0=
0,
b0 D
#475001
0)
#480001
1)
02
04
05
#485001
0)
#490001
1)
#495001
0)
#500001
1)
1E
0H
1=
#505001
0)
#510001
1)
0=
b0 C
0E
0J
0G
#510002
bx 7
bx 0
bx K
bx 8
bx O
bx 6
bx 1
bx /
#515002
0)
#520002
1)
1=
1E
#525002
0)
#530002
1)
0E
0=
1.
0I
#535002
0)
#540002
1)
#545002
0)
#550002
1)
0.
#555002
0)
#560002
1)
1=
1E
#565002
0)
#570002
1)
#575002
0)
#580002
1)
#585002
0)
#590002
1)
#595002
0)
#600002
1)
b10 8
1P
1-
1@
b10101010101010101010101010101010 K
b1111111111 7
b1111 O
1:
1<
b111111111100 6
1M
#605002
0)
#610002
1)
0M
1A
1;
1N
0@
0-
1L
1?
19
0:
#615002
0)
#620002
1)
0?
0A
0L
0;
0P
0N
09
0<
#625002
0)
#630002
1)
#635002
0)
#640002
1)
1<
1P
1:
1M
1-
1@
b10000000000 7
b1000000000000 6
#645002
0)
#650002
1)
0-
0M
1A
1?
0:
1L
1;
19
0@
1N
#655002
0)
#660002
1)
0N
0P
0<
0L
0?
0A
09
0;
#665002
0)
#670002
1)
#675002
0)
#680002
1)
b10101010 K
b1000000000100 6
1:
1-
1<
1M
1P
b10000000001 7
b1 O
1@
#685002
0)
#690002
1)
0@
0M
1?
1;
1N
1L
0-
0:
19
1A
#695002
0)
#700002
1)
0A
0?
0L
0<
0N
0;
09
0P
#705002
0)
#710002
1)
#715002
0)
#720002
1)
1P
1-
1M
1@
1<
b0 K
b1000000000000 6
1:
b10000000000 7
#725002
0)
#730002
1)
1N
0-
0M
1A
0@
1L
1?
0:
1;
19
#735002
0)
#740002
1)
09
0L
0P
0N
0<
0A
0;
0?
#745002
0)
#750002
1)
#755002
0)
#760002
1)
15
13
b111111111111 /
b1111111111 0
b10 1
1,
1H
#765002
0)
#770002
1)
0H
1G
b10101010 D
1J
03
14
12
b10101010 B
0,
#775002
0)
#780002
1)
02
0G
04
05
1I
0J
b10101010 C
#785002
0)
#790002
1)
0I
#795002
0)
#800002
1)
1,
b1000000000000 /
1H
15
13
b10000000000 0
#805002
0)
#810002
1)
1J
0,
0H
1G
12
b0 D
14
03
b0 B
#815002
0)
#820002
1)
05
1I
02
0J
0G
b0 C
04
#820003
bx K
bx 0
bx 8
bx 7
0E
0=
bx /
bx 1
bx O
bx 6
#825003
0)
#830003
1)
1=
1E
#835003
0)
#840003
1)
0E
0=
1.
0I
#845003
0)
#850003
1)
#855003
0)
#860003
1)
0.
#865003
0)
#870003
1)
1=
1E
#875003
0)
#880003
1)
#885003
0)
#890003
1)
0E
0=
#895003
0)
#900003
1)
#905003
0)
#910003
1)
b111111111100 6
b10 8
1<
b10101010101010101010101010101010 K
1@
b1111111111 7
1-
1P
1M
b1111 O
1:
#915003
0)
#920003
1)
0:
1=
1?
19
0-
1E
1L
1N
0@
1;
1A
0M
#925003
0)
#930003
1)
0N
0P
0=
0L
0?
09
0E
0<
0A
0;
#935003
0)
#940003
1)
#945003
0)
#950003
1)
1M
1:
b1000000000000 6
1-
1P
b10000000000 7
1@
1<
#955003
0)
#960003
1)
1E
0M
1;
1N
0-
0:
1=
19
1L
1?
0@
1A
#965003
0)
#970003
1)
0A
0L
0P
0E
0<
09
0;
0N
0=
0?
#975003
0)
#980003
1)
#985003
0)
#990003
1)
1P
1M
1<
1-
b1000000000100 6
b10101010 K
1:
1@
b1 O
b10000000001 7
#995003
0)
#1000003
1)
1N
1?
1L
1A
1;
1E
0-
0M
19
0:
1=
0@
#1005003
0)
#1010003
1)
0?
0N
0L
0P
0E
0;
0A
0<
0=
09
#1015003
0)
#1020003
1)
#1025003
0)
#1030003
1)
b0 K
1@
1M
b10000000000 7
1-
b1000000000000 6
1P
1<
1:
#1035003
0)
#1040003
1)
0:
1A
0@
19
0-
0M
1?
1;
1L
1N
1E
1=
#1045003
0)
#1050003
1)
0=
0N
0A
0L
09
0;
0?
0E
0<
0P
#1055003
0)
#1060003
1)
#1065003
0)
#1070003
1)
b1111111111 0
1H
1,
15
b111111111111 /
13
b10 1
#1075003
0)
#1080003
1)
b10101010 D
b10101010 B
1G
1=
14
0,
0H
1J
12
03
1E
#1085003
0)
#1090003
1)
0E
0J
0G
04
0=
1I
05
b10101010 C
02
#1095003
0)
#1100003
1)
#1105003
0)
#1110003
1)
1H
b10000000000 0
1,
13
15
b1000000000000 /
#1115003
0)
#1120003
1)
1=
1E
b0 B
b0 D
12
14
1J
0H
1G
03
0,
#1125003
0)
#1130003
1)
0E
0=
0J
04
02
b0 C
0G
05
#1130004
bx 1
bx 8
bx 6
bx K
bx /
bx 0
bx 7
bx O
#1135004
0)
#1140004
1)
1=
1E
#1145004
0)
#1150004
1)
0E
0=
1.
0I
#1155004
0)
#1160004
1)
#1165004
0)
#1170004
1)
0.
#1175004
0)
#1180004
1)
1=
1E
#1185004
0)
#1190004
1)
#1195004
0)
#1200004
1)
b1000000000000 6
1P
b10 8
1:
1@
1-
b1 O
b0 K
1M
b10000000000 7
1<
#1205004
0)
#1210004
1)
1;
19
1N
0-
0@
0:
1A
1L
0M
1?
#1215004
0)
#1220004
1)
0?
0<
0P
0A
09
0;
0N
0L
#1225004
0)
#1230004
1)
b10000000000 0
15
1,
b10 1
1H
b1000000000000 /
13
#1235004
0)
#1240004
1)
03
0H
14
0,
1J
1G
12
#1245004
0)
#1250004
1)
02
05
04
1I
0G
0J
#1255004
0)
#1260004
1)
b1000000000001 6
1:
b10 O
1<
1@
1P
1-
1M
0I
#1265004
0)
#1270004
1)
1L
1;
1?
0@
19
1A
0:
0M
1N
0-
#1275004
0)
#1280004
1)
0A
0L
09
0P
0<
0?
0;
0N
#1285004
0)
#1290004
1)
1H
1,
13
15
b1000000000001 /
#1295004
0)
#1300004
1)
03
1J
0H
14
0,
12
1G
#1305004
0)
#1310004
1)
0G
1I
0J
04
02
05
#1315004
0)
#1320004
1)
1-
0I
1<
1P
b1000000000010 6
1@
b100 O
1:
1M
#1325004
0)
#1330004
1)
0M
1?
1N
0@
1A
0-
19
1L
0:
1;
#1335004
0)
#1340004
1)
0;
09
0?
0A
0P
0<
0N
0L
#1345004
0)
#1350004
1)
15
1,
b1000000000010 /
13
1H
#1355004
0)
#1360004
1)
0H
03
0,
1G
1J
14
12
#1365004
0)
#1370004
1)
02
0G
05
1I
04
0J
#1375004
0)
#1380004
1)
1<
1M
1-
b1000000000011 6
1P
1@
0I
1:
b1000 O
#1385004
0)
#1390004
1)
1L
0-
1;
1A
0M
1?
19
0:
0@
1N
#1395004
0)
#1400004
1)
0N
0P
0?
0<
0A
0;
0L
09
#1405004
0)
#1410004
1)
15
1,
13
1H
b1000000000011 /
#1415004
0)
#1420004
1)
0H
0,
1J
12
03
1G
14
#1425004
0)
#1430004
1)
04
05
02
0J
0G
1I
#1435004
0)
#1440004
1)
0I
b11 O
b100000000 K
1<
1M
b1000000000000 6
1P
1-
1@
1:
#1445004
0)
#1450004
1)
0:
19
1;
1N
0M
1A
1?
0@
0-
1L
#1455004
0)
#1460004
1)
0L
0A
0P
0N
09
0;
0<
0?
#1465004
0)
#1470004
1)
13
1H
b1000000000000 /
1,
15
#1475004
0)
#1480004
1)
0,
12
0H
03
14
b1 B
b1 D
1G
1J
#1485004
0)
#1490004
1)
0J
05
02
1I
04
0G
b1 C
#1490005
0E
bx 0
bx 6
bx 1
bx 8
0=
bx /
bx O
bx K
bx 7
#1495005
0)
#1500005
1)
1E
1=
#1505005
0)
#1510005
1)
0=
0I
0E
1.
#1515005
0)
#1520005
1)
#1525005
0)
#1530005
1)
0.
#1535005
0)
#1540005
1)
1=
1E
#1545005
0)
#1550005
1)
#1555005
0)
#1560005
1)
0E
1:
b1 O
b1000000000000 6
b10000000000 7
1M
b10 8
1P
0=
b0 K
1<
1@
1-
#1565005
0)
#1570005
1)
0-
1L
1?
1;
0M
0:
1N
19
1A
#1575005
0)
#1580005
1)
09
0L
0N
0;
0<
0P
#1585005
0)
#1590005
1)
1E
0@
1=
#1595005
0)
#1600005
1)
0=
0A
0?
0E
#1605005
0)
#1610005
1)
15
1,
b10 1
13
b1000000000000 /
1H
b10000000000 0
#1615005
0)
#1620005
1)
b0 B
1J
03
12
0,
1G
14
b0 D
#1625005
0)
#1630005
1)
02
0H
1I
b0 C
1E
1=
05
04
#1635005
0)
#1640005
1)
0=
0E
0J
0G
#1645005
0)
#1650005
1)
1-
1P
1:
1M
b1000000000001 6
b10 O
1<
1@
#1655005
0)
#1660005
1)
1A
1N
0M
0:
1L
19
0-
1?
1;
#1665005
0)
#1670005
1)
0;
09
0@
0L
1=
0N
1E
0P
0<
#1675005
0)
#1680005
1)
0E
0I
0=
0A
0?
#1685005
0)
#1690005
1)
1H
b1000000000001 /
13
15
1,
#1695005
0)
#1700005
1)
0,
1G
14
12
1J
03
#1705005
0)
#1710005
1)
04
1=
0H
1I
1E
05
02
#1715005
0)
#1720005
1)
0G
0=
0J
0E
#1725005
0)
#1730005
1)
1<
b1000000000010 6
1:
1M
1@
1-
b100 O
1P
#1735005
0)
#1740005
1)
0M
1;
1?
0:
19
1N
1L
0-
1A
#1745005
0)
#1750005
1)
0N
1E
0P
09
0;
0<
0@
0L
1=
#1755005
0)
#1760005
1)
0=
0A
0I
0E
0?
#1765005
0)
#1770005
1)
13
1,
b1000000000010 /
1H
15
#1775005
0)
#1780005
1)
12
0,
14
03
1G
1J
#1785005
0)
#1790005
1)
05
1=
1E
04
1I
02
0H
#1795005
0)
#1800005
1)
0J
0=
0E
0G
#1805005
0)
#1810005
1)
1M
b1000000000011 6
1:
1P
1-
b1000 O
1@
1<
#1815005
0)
#1820005
1)
1;
1?
1N
0:
19
1A
0M
1L
0-
#1825005
0)
#1830005
1)
0;
0<
09
0N
1=
0L
0@
0P
1E
#1835005
0)
#1840005
1)
0E
0A
0I
0?
0=
#1845005
0)
#1850005
1)
b1000000000011 /
1H
15
13
1,
#1855005
0)
#1860005
1)
0,
03
1G
14
1J
12
#1865005
0)
#1870005
1)
02
04
1I
1E
1=
05
0H
#1875005
0)
#1880005
1)
0=
0G
0E
0J
#1885005
0)
#1890005
1)
1-
b1000000000000 6
1<
1:
1P
1@
b100000000 K
1M
b11 O
#1895005
0)
#1900005
1)
1N
19
1A
0-
1;
0M
1?
0:
1L
#1905005
0)
#1910005
1)
0L
0<
09
1=
0N
0P
1E
0;
0@
#1915005
0)
#1920005
1)
0I
0=
0A
0?
0E
#1925005
0)
#1930005
1)
1,
b1000000000000 /
15
1H
13
#1935005
0)
#1940005
1)
03
b1 D
0,
1J
14
12
b1 B
1G
#1945005
0)
#1950005
1)
0H
1E
02
05
1I
b1 C
1=
04
#1955005
0)
#1960005
1)
0=
0G
0J
0E
#1960006
bx O
bx 8
bx 0
bx 1
bx 7
bx /
bx 6
bx K
#1965006
0)
#1970006
1)
1=
1E
#1975006
0)
#1980006
1)
0E
0=
1.
0I
#1985006
0)
#1990006
1)
#1995006
0)
#2000006
1)
0.
#2005006
0)
#2010006
1)
1=
1E
#2015006
0)
#2020006
1)
#2025006
0)
#2030006
1)
#2035006
0)
#2040006
1)
#2045006
0)
#2050006
1)
1@
b0 K
b1 O
b10000000000 7
1-
1<
b10 8
b1000000000000 6
1P
1:
1M
#2055006
0)
#2060006
1)
0M
0@
0-
19
1L
0:
1;
1N
1?
1A
#2065006
0)
#2070006
1)
0A
09
0<
0?
0P
0L
0N
0;
#2075006
0)
#2080006
1)
#2085006
0)
#2090006
1)
b1000000000000 /
13
1,
15
1H
b10 1
b10000000000 0
#2095006
0)
#2100006
1)
1J
b0 B
14
b0 D
0H
03
1G
12
0,
#2105006
0)
#2110006
1)
02
1I
0J
0G
04
b0 C
05
#2115006
0)
#2120006
1)
0I
#2125006
0)
#2130006
1)
1-
1@
1M
b10 O
1:
1<
b1000000000001 6
1P
#2135006
0)
#2140006
1)
19
1;
1A
0M
0@
0-
0:
1?
1N
1L
#2145006
0)
#2150006
1)
0L
09
0P
0A
0;
0N
0?
0<
#2155006
0)
#2160006
1)
#2165006
0)
#2170006
1)
1,
b1000000000001 /
15
1H
13
#2175006
0)
#2180006
1)
03
0H
12
0,
14
1J
1G
#2185006
0)
#2190006
1)
0G
0J
04
02
05
1I
#2195006
0)
#2200006
1)
0I
#2205006
0)
#2210006
1)
1<
1@
1P
1M
1:
b1000000000010 6
1-
b100 O
#2215006
0)
#2220006
1)
1A
1L
0@
19
0-
1?
0:
0M
1N
1;
#2225006
0)
#2230006
1)
0;
0P
0L
0A
0<
0N
0?
09
#2235006
0)
#2240006
1)
#2245006
0)
#2250006
1)
15
13
1H
b1000000000010 /
1,
#2255006
0)
#2260006
1)
0,
0H
1J
1G
12
03
14
#2265006
0)
#2270006
1)
04
1I
02
0G
0J
05
#2275006
0)
#2280006
1)
0I
#2285006
0)
#2290006
1)
1@
b1000 O
1P
b1000000000011 6
1<
1-
1M
1:
#2295006
0)
#2300006
1)
0:
1A
19
0@
1L
1;
0M
1N
1?
0-
#2305006
0)
#2310006
1)
0L
0A
09
0?
0;
0P
0N
0<
#2315006
0)
#2320006
1)
#2325006
0)
#2330006
1)
b1000000000011 /
13
1H
1,
15
#2335006
0)
#2340006
1)
1J
0,
0H
03
1G
12
14
#2345006
0)
#2350006
1)
04
05
1I
02
0G
0J
#2355006
0)
#2360006
1)
0I
#2365006
0)
#2370006
1)
1<
1-
1:
b11 O
1@
b100000000 K
b1000000000000 6
1M
1P
#2375006
0)
#2380006
1)
0@
0-
0:
1A
1L
0M
1?
1N
19
1;
#2385006
0)
#2390006
1)
0;
0A
0P
0<
09
0?
0L
0N
#2395006
0)
#2400006
1)
#2405006
0)
#2410006
1)
15
b1000000000000 /
13
1H
1,
#2415006
0)
#2420006
1)
0,
1G
14
b1 B
0H
1J
b1 D
03
12
#2425006
0)
#2430006
1)
02
b1 C
0G
1I
04
0J
05
#2430007
bx 1
bx 0
0E
bx O
0=
bx 7
bx /
bx K
bx 8
bx 6
#2435007
0)
#2440007
1)
1=
1E
#2445007
0)
#2450007
1)
0E
0=
0I
1.
#2455007
0)
#2460007
1)
#2465007
0)
#2470007
1)
0.
#2475007
0)
#2480007
1)
1=
1E
#2485007
0)
#2490007
1)
#2495007
0)
#2500007
1)
0E
0=
#2505007
0)
#2510007
1)
#2515007
0)
#2520007
1)
b10000000000 7
1P
1@
1:
b1000000000000 6
1-
b1 O
b10 8
1<
1M
b0 K
#2525007
0)
#2530007
1)
0-
1=
1A
1;
1N
1E
0:
0@
0M
1L
19
1?
#2535007
0)
#2540007
1)
0?
0=
0E
0A
0N
0P
0;
09
0L
0<
#2545007
0)
#2550007
1)
#2555007
0)
#2560007
1)
13
b10 1
15
1,
b10000000000 0
1H
b1000000000000 /
#2565007
0)
#2570007
1)
1J
12
03
0,
b0 D
14
b0 B
1=
1G
1E
0H
#2575007
0)
#2580007
1)
0G
b0 C
0J
0=
02
05
1I
04
0E
#2585007
0)
#2590007
1)
#2595007
0)
#2600007
1)
1P
1<
1:
1-
b1000000000001 6
1@
1M
b10 O
#2605007
0)
#2610007
1)
0-
1E
0:
1N
1?
1=
1A
0M
0@
1L
19
1;
#2615007
0)
#2620007
1)
0;
0=
0I
0<
0P
0?
0E
0N
09
0A
0L
#2625007
0)
#2630007
1)
#2635007
0)
#2640007
1)
1H
b1000000000001 /
15
1,
13
#2645007
0)
#2650007
1)
03
0,
1E
1G
1=
0H
1J
12
14
#2655007
0)
#2660007
1)
04
0J
0E
1I
05
0=
0G
02
#2665007
0)
#2670007
1)
#2675007
0)
#2680007
1)
b100 O
1<
1-
1P
1:
1M
b1000000000010 6
1@
#2685007
0)
#2690007
1)
0@
1=
1L
1;
0-
1?
1E
0:
1A
1N
0M
19
#2695007
0)
#2700007
1)
09
0?
0=
0L
0P
0;
0I
0<
0E
0N
0A
#2705007
0)
#2710007
1)
#2715007
0)
#2720007
1)
1,
13
15
1H
b1000000000010 /
#2725007
0)
#2730007
1)
0H
1J
14
12
03
0,
1=
1G
1E
#2735007
0)
#2740007
1)
0E
0J
1I
04
05
02
0G
0=
#2745007
0)
#2750007
1)
#2755007
0)
#2760007
1)
1@
1-
1P
b1000 O
b1000000000011 6
1M
1:
1<
#2765007
0)
#2770007
1)
1=
1A
19
1E
1;
1?
0-
0@
1L
0:
1N
0M
#2775007
0)
#2780007
1)
0A
0<
0=
09
0P
0?
0I
0;
0E
0N
0L
#2785007
0)
#2790007
1)
#2795007
0)
#2800007
1)
1,
b1000000000011 /
15
1H
13
#2805007
0)
#2810007
1)
03
0H
0,
14
1J
1=
1E
1G
12
#2815007
0)
#2820007
1)
02
0J
04
1I
05
0G
0=
0E
#2825007
0)
#2830007
1)
#2835007
0)
#2840007
1)
b100000000 K
1@
1M
1-
1<
1P
b1000000000000 6
b11 O
1:
#2845007
0)
#2850007
1)
0:
1L
1;
1A
1E
0-
0@
0M
1?
19
1=
1N
#2855007
0)
