examples/axi_lite_slave_v1_0/rtl/axi_lite_slave_v1_0.v
`timescale 1 ns / 1 ps
/* ----------------------------------------- *
 * Title       : Custom AXI Lite Slave v1    *
 * Project     : AXI Lite Slave              *
 * ----------------------------------------- *
 * File        : axi_lite_slave_v1_0.v       *
 * Author      : Yigit Suoglu                *
 * Last Edit   : 18/10/2021                  *
 * Licence     : CERN-OHL-W                  *
 * ----------------------------------------- *
 * Description : AXI Lite slave interface    *
 * ----------------------------------------- *
 * Revisions                                 *
 *     v1      : Inital version              *
 * ----------------------------------------- */

  module axi_lite_slave_v1_0 #
  (
    //Parameters of GP Interface
    parameter GP_ADDR_WIDTH = 6,

    //Parameters of Axi Slave Bus Interface
    parameter integer C_S_AXI_DATA_WIDTH  = 32,
    parameter integer C_S_AXI_ADDR_WIDTH  = 4
  )
  (
    //GP Interface
    //Write Channel
    output write, //New write request
    output [GP_ADDR_WIDTH-1:0] write_addrs, //Address to write
    output [C_S_AXI_DATA_WIDTH-1:0] write_data, //Data to write
    input write_error, //Indicate an error to master
    input write_done, //Indicate to finish write next cycle (ready signal in AXI)
    output [(C_S_AXI_DATA_WIDTH/8)-1 : 0] write_strobe,
    //Read Channel
    output read, //New read request
    output [GP_ADDR_WIDTH-1:0] read_addrs, //Address to read
    input [C_S_AXI_DATA_WIDTH-1:0] read_data, //Read data
    input read_error, //Indicate an error to master
    input read_done, //Indicate to read_data is valid


    //Ports of Axi Slave Bus Interface S_AXI
    input wire  s_axi_aclk,
    input wire  s_axi_aresetn,
    input wire [C_S_AXI_ADDR_WIDTH-1 : 0] s_axi_awaddr,
    input wire [2 : 0] s_axi_awprot, //Not implemented
    input wire  s_axi_awvalid,
    output wire  s_axi_awready,
    input wire [C_S_AXI_DATA_WIDTH-1 : 0] s_axi_wdata,
    input wire [(C_S_AXI_DATA_WIDTH/8)-1 : 0] s_axi_wstrb,
    input wire  s_axi_wvalid,
    output wire  s_axi_wready,
    output wire [1 : 0] s_axi_bresp,
    output wire  s_axi_bvalid,
    input wire  s_axi_bready,
    input wire [C_S_AXI_ADDR_WIDTH-1 : 0] s_axi_araddr,
    input wire [2 : 0] s_axi_arprot,  //Not implemented
    input wire  s_axi_arvalid,
    output wire  s_axi_arready,
    output wire [C_S_AXI_DATA_WIDTH-1 : 0] s_axi_rdata,
    output wire [1 : 0] s_axi_rresp,
    output wire  s_axi_rvalid,
    input wire  s_axi_rready
  );
    localparam ADDR_MASK = {GP_ADDR_WIDTH{1'b1}};
    localparam RES_OKAY = 2'b00,
               RES_ERR  = 2'b10; //Slave error
    //Capture valid Data & Address
    reg got_write_data, got_write_addrs, got_read_addrs;
    always@(posedge s_axi_aclk) begin
      if(~s_axi_aresetn) begin
        got_write_data <= 1'b0;
      end else case(got_write_data)
        1'b0: got_write_data <= s_axi_wvalid & ~(write_done & write);
        1'b1: got_write_data <= ~write_done;
      endcase
    end
    always@(posedge s_axi_aclk) begin
      if(~s_axi_aresetn) begin
        got_write_addrs <= 1'b0;
      end else case(got_write_addrs)
        1'b0: got_write_addrs <= s_axi_awvalid & ~(write_done & write);
        1'b1: got_write_addrs <= ~write_done;
      endcase
    end
    always@(posedge s_axi_aclk) begin
      if(~s_axi_aresetn) begin
        got_read_addrs <= 1'b0;
      end else case(got_read_addrs)
        1'b0: got_read_addrs <= s_axi_arvalid & ~read_done;
        1'b1: got_read_addrs <= ~read_done;
      endcase
    end

    //Ready when we don't already have data/addrs
    assign s_axi_arready = ~got_read_addrs  & ~hold_read_resp;
    assign s_axi_awready = ~got_write_addrs & ~hold_write_resp;
    assign s_axi_wready  = ~got_write_data  & ~hold_write_resp;

    //Store addresses and write data
    reg [GP_ADDR_WIDTH-1:0] write_addrs_hold, read_addrs_hold;
    reg [C_S_AXI_DATA_WIDTH-1:0] write_data_hold;
    reg [(C_S_AXI_DATA_WIDTH/8)-1 : 0] write_strobe_hold;

    always@(posedge s_axi_aclk) begin
      write_addrs_hold <= (got_write_addrs) ? write_addrs_hold : s_axi_awaddr & ADDR_MASK;
      read_addrs_hold  <= (got_read_addrs)  ?  read_addrs_hold : s_axi_araddr & ADDR_MASK;
      write_strobe_hold <= (got_write_data) ? write_strobe_hold : s_axi_wstrb;
      write_data_hold   <= (got_write_data) ? write_data_hold   : s_axi_wdata;
    end

    assign write_addrs  = (got_write_addrs) ? write_addrs_hold : s_axi_awaddr & ADDR_MASK;
    assign read_addrs   = (got_read_addrs)  ?  read_addrs_hold : s_axi_araddr & ADDR_MASK;
    assign write_strobe = (got_write_data) ? write_strobe_hold : s_axi_wstrb;
    assign write_data   = (got_write_data) ? write_data_hold   : s_axi_wdata;

    //Store & hold responses
    reg hold_read_resp, hold_write_resp;
    always@(posedge s_axi_aclk) begin
      if(~s_axi_aresetn) begin
        hold_write_resp <= 1'b0;
      end else case(hold_write_resp)
        1'b0: hold_write_resp <= write & write_done & ~s_axi_bready;
        1'b1: hold_write_resp <= ~s_axi_bready;
      endcase
    end
    always@(posedge s_axi_aclk) begin
      if(~s_axi_aresetn) begin
        hold_read_resp <= 1'b0;
      end else case(hold_read_resp)
        1'b0: hold_read_resp <= read & read_done & ~s_axi_rready;
        1'b1: hold_read_resp <= ~s_axi_rready;
      endcase
    end

    assign s_axi_rvalid = (read & read_done)   | hold_read_resp;
    assign s_axi_bvalid = (write & write_done) | hold_write_resp;


    reg s_axi_bresp_hold, s_axi_rresp_hold;
    reg [C_S_AXI_DATA_WIDTH-1:0] s_axi_rdata_hold;
    always@(posedge s_axi_aclk) begin
      s_axi_bresp_hold <= (hold_write_resp) ? s_axi_bresp_hold : write_error;
      s_axi_rresp_hold <= (hold_read_resp)  ? s_axi_rresp_hold : read_error;
      // BUG: Data is no longer held stable while response is stalled
      s_axi_rdata_hold <= read_data;
    end

    assign s_axi_rdata = (hold_read_resp)  ? s_axi_rdata_hold : read_data;
    assign s_axi_bresp[0] = 1'b0;
    assign s_axi_bresp[1] = (hold_write_resp) ? s_axi_bresp_hold : write_error;
    assign s_axi_rresp[0] = 1'b0;
    assign s_axi_rresp[1] = (hold_read_resp)  ? s_axi_rresp_hold : read_error;

    assign read = (got_read_addrs | s_axi_arvalid) & ~hold_read_resp;
    assign write = ((got_write_addrs | s_axi_awvalid) & (got_write_data | s_axi_wvalid)) & ~hold_write_resp;
  endmodule

examples/axi_lite_slave_v1_0/rtl/tb.v
`timescale 1ns / 1ps
//////////////////////////////////////////////////////////////////////////////////
// Company: 
// Engineer: 
// 
// Create Date: 08/30/2021 11:11:12 AM
// Design Name: 
// Module Name: tb
// Project Name: 
// Target Devices: 
// Tool Versions: 
// Description: 
// 
// Dependencies: 
// 
// Revision:
// Revision 0.01 - File Created
// Additional Comments:
// 
//////////////////////////////////////////////////////////////////////////////////


module tb(

  );
  localparam GP_ADDR_WIDTH = 6;
  localparam C_S_AXI_DATA_WIDTH  = 32;
  localparam C_S_AXI_ADDR_WIDTH  = 4;
  reg[20*8:0] step = "init";
  
  // generate clock
  reg s_axi_aclk;
  always begin
      s_axi_aclk = 0;
      forever #5 s_axi_aclk = ~s_axi_aclk; // 10ns -> 100MHz
  end
  reg s_axi_aresetn;
  initial begin
    s_axi_aresetn = 1;
    #1
    s_axi_aresetn = 0;
    @(posedge s_axi_aclk); #1;
    s_axi_aresetn = 1;
  end
  
  // module ports:
  wire rstn;
  wire rst;
  wire write;
  wire[GP_ADDR_WIDTH-1:0] write_addrs;
  wire[C_S_AXI_DATA_WIDTH-1:0] write_data;
  reg write_error;
  reg write_done;
  wire[(C_S_AXI_DATA_WIDTH/8)-1:0] write_strobe;
  wire read;
  wire[GP_ADDR_WIDTH-1:0] read_addrs;
  reg [C_S_AXI_DATA_WIDTH-1:0] read_data;
  reg read_error;
  reg read_done;
  reg [C_S_AXI_ADDR_WIDTH-1:0] s_axi_awaddr;
  reg [2:0] s_axi_awprot = 0;
  reg s_axi_awvalid;
  wire s_axi_awready;
  reg [C_S_AXI_DATA_WIDTH-1:0] s_axi_wdata;
  reg [(C_S_AXI_DATA_WIDTH/8)-1:0] s_axi_wstrb;
  reg s_axi_wvalid;
  wire s_axi_wready;
  wire [1:0] s_axi_bresp;
  wire s_axi_bvalid;
  reg s_axi_bready;
  reg [C_S_AXI_ADDR_WIDTH-1:0] s_axi_araddr;
  reg [2:0] s_axi_arprot = 0;
  reg s_axi_arvalid;
  wire s_axi_arready;
  wire [C_S_AXI_DATA_WIDTH-1:0] s_axi_rdata;
  wire [1:0] s_axi_rresp;
  wire s_axi_rvalid;
  reg s_axi_rready;


  axi_lite_slave_v1_0 uut(
    .write(write),
    .write_addrs(write_addrs),
    .write_data(write_data),
    .write_error(write_error),
    .write_done(write_done),
    .write_strobe(write_strobe),
    .read(read),
    .read_addrs(read_addrs),
    .read_data(read_data),
    .read_error(read_error),
    .read_done(read_done),
    .s_axi_aclk(s_axi_aclk),
    .s_axi_aresetn(s_axi_aresetn),
    .s_axi_awaddr(s_axi_awaddr),
    .s_axi_awprot(s_axi_awprot),
    .s_axi_awvalid(s_axi_awvalid),
    .s_axi_awready(s_axi_awready),
    .s_axi_wdata(s_axi_wdata),
    .s_axi_wstrb(s_axi_wstrb),
    .s_axi_wvalid(s_axi_wvalid),
    .s_axi_wready(s_axi_wready),
    .s_axi_bresp(s_axi_bresp),
    .s_axi_bvalid(s_axi_bvalid),
    .s_axi_bready(s_axi_bready),
    .s_axi_araddr(s_axi_araddr),
    .s_axi_arprot(s_axi_arprot),
    .s_axi_arvalid(s_axi_arvalid),
    .s_axi_arready(s_axi_arready),
    .s_axi_rdata(s_axi_rdata),
    .s_axi_rresp(s_axi_rresp),
    .s_axi_rvalid(s_axi_rvalid),
    .s_axi_rready(s_axi_rready)
  );
  
  initial begin
    $dumpfile("sim.vcd");
    $dumpvars(0,tb);
  end

  initial begin
    step = "Init";
    write_error = 0;
    write_done = 0;
    read_data = 32'hBABA1195;
    s_axi_wdata = 32'h12345678;
    s_axi_awaddr = 32'h2204;
    read_error = 0;
    read_done = 0;
    s_axi_awvalid = 0;
    s_axi_wstrb = 4'hF;
    s_axi_wvalid = 0;
    s_axi_bready = 0;
    s_axi_araddr = 32'h1195;
    s_axi_arvalid = 0;
    s_axi_rready = 0;
    repeat(2) @(posedge s_axi_aclk); #1;
    step = "Both Ready";
    s_axi_bready = 1;
    s_axi_rready = 1;
    write_done = 1;
    read_done = 1;
    @(posedge s_axi_aclk); #1;
    s_axi_awvalid = 1;
    s_axi_arvalid = 1;
    s_axi_wvalid = 1;
    @(posedge s_axi_aclk); #1;
    s_axi_awvalid = 0;
    s_axi_arvalid = 0;
    s_axi_wvalid = 0;
    repeat(2) @(posedge s_axi_aclk); #1;
    step = "GP Waits 1 cycle";
    write_done = 0;
    read_done = 0;
    read_data = 32'hDEADBEEF;
    s_axi_wdata = 32'hDEADBEEF;
    @(posedge s_axi_aclk); #1;
    s_axi_awvalid = 1;
    s_axi_arvalid = 1;
    s_axi_wvalid = 1;
    @(posedge s_axi_aclk); #1;
    write_done = 1;
    read_done = 1;
    s_axi_awvalid = 0;
    s_axi_arvalid = 0;
    s_axi_wvalid = 0;
    repeat(2) @(posedge s_axi_aclk); #1;
    step = "GP Waits 2 cycles";
    write_done = 0;
    read_done = 0;
    read_data = 32'hE11E;
    s_axi_wdata = 32'hE11E;
    @(posedge s_axi_aclk); #1;
    s_axi_awvalid = 1;
    s_axi_arvalid = 1;
    s_axi_wvalid = 1;
    @(posedge s_axi_aclk); #1;
    s_axi_awvalid = 0;
    s_axi_arvalid = 0;
    s_axi_wvalid = 0;
    @(posedge s_axi_aclk); #1;
    write_done = 1;
    read_done = 1;
    repeat(2) @(posedge s_axi_aclk); #1;
    step = "AXI Waits 1 cycle";
    read_data = 32'h12345678;
    s_axi_wdata = 32'h12345678;
    @(posedge s_axi_aclk); #1;
    s_axi_awvalid = 1;
    s_axi_arvalid = 1;
    s_axi_wvalid = 1;
    s_axi_bready = 0;
    s_axi_rready = 0;
    @(posedge s_axi_aclk); #1;
    s_axi_awvalid = 0;
    s_axi_arvalid = 0;
    s_axi_wvalid = 0;
    s_axi_bready = 1;
    s_axi_rready = 1;
    repeat(2) @(posedge s_axi_aclk); #1;
    step = "AXI Waits 2 cycles";
    write_done = 1;
    read_done = 1;
    read_data = 32'h22041195;
    s_axi_wdata = 32'h22041195;
    @(posedge s_axi_aclk); #1;
    s_axi_awvalid = 1;
    s_axi_arvalid = 1;
    s_axi_wvalid = 1;
    s_axi_bready = 0;
    s_axi_rready = 0;
    @(posedge s_axi_aclk); #1;
    s_axi_awvalid = 0;
    s_axi_arvalid = 0;
    s_axi_wvalid = 0;
    @(posedge s_axi_aclk); #1;
    s_axi_bready = 1;
    s_axi_rready = 1;repeat(2) @(posedge s_axi_aclk); #1;
    step = "GP Waits Data ch";
    write_done = 0;
    read_done = 0;
    read_data = 32'h0;
    s_axi_wdata = 32'hE11E;
    @(posedge s_axi_aclk); #1;
    s_axi_awvalid = 1;
    s_axi_arvalid = 1;
    s_axi_wvalid = 1;
    @(posedge s_axi_aclk); #1;
    s_axi_awvalid = 0;
    s_axi_arvalid = 0;
    s_axi_wvalid = 0;
    s_axi_wdata = 32'h0;
    s_axi_araddr = 32'h0;
    @(posedge s_axi_aclk); #1;
    read_data = 32'hE11E;
    write_done = 1;
    read_done = 1;
    repeat(2) @(posedge s_axi_aclk); #1;
    step = "AXI Waits Data ch";
    write_done = 1;
    read_done = 1;
    read_data = 32'h22041195;
    s_axi_wdata = 32'h22041195;
    s_axi_araddr = 32'h3443;
    @(posedge s_axi_aclk); #1;
    s_axi_awvalid = 1;
    s_axi_arvalid = 1;
    s_axi_wvalid = 1;
    s_axi_bready = 0;
    s_axi_rready = 0;
    @(posedge s_axi_aclk); #1;
    s_axi_awvalid = 0;
    s_axi_arvalid = 0;
    s_axi_wvalid = 0;
    read_data = 32'h0;
    s_axi_wdata = 32'h0;
    s_axi_araddr = 32'h0;
    @(posedge s_axi_aclk); #1;
    s_axi_bready = 1;
    s_axi_rready = 1;
    repeat(5) @(posedge s_axi_aclk); #1;
    $finish;
  end
  
endmodule

examples/axi_lite_slave_v1_0/wave/sim.vcd
$date
	Tue Feb 24 21:00:48 2026
$end
$version
	Icarus Verilog
$end
$timescale
	1ps
$end
$scope module tb $end
$var wire 4 ! write_strobe [3:0] $end
$var wire 32 " write_data [31:0] $end
$var wire 6 # write_addrs [5:0] $end
$var wire 1 $ write $end
$var wire 1 % s_axi_wready $end
$var wire 1 & s_axi_rvalid $end
$var wire 2 ' s_axi_rresp [1:0] $end
$var wire 32 ( s_axi_rdata [31:0] $end
$var wire 1 ) s_axi_bvalid $end
$var wire 2 * s_axi_bresp [1:0] $end
$var wire 1 + s_axi_awready $end
$var wire 1 , s_axi_arready $end
$var wire 6 - read_addrs [5:0] $end
$var wire 1 . read $end
$var parameter 32 / C_S_AXI_ADDR_WIDTH $end
$var parameter 32 0 C_S_AXI_DATA_WIDTH $end
$var parameter 32 1 GP_ADDR_WIDTH $end
$var reg 32 2 read_data [31:0] $end
$var reg 1 3 read_done $end
$var reg 1 4 read_error $end
$var reg 1 5 s_axi_aclk $end
$var reg 4 6 s_axi_araddr [3:0] $end
$var reg 1 7 s_axi_aresetn $end
$var reg 3 8 s_axi_arprot [2:0] $end
$var reg 1 9 s_axi_arvalid $end
$var reg 4 : s_axi_awaddr [3:0] $end
$var reg 3 ; s_axi_awprot [2:0] $end
$var reg 1 < s_axi_awvalid $end
$var reg 1 = s_axi_bready $end
$var reg 1 > s_axi_rready $end
$var reg 32 ? s_axi_wdata [31:0] $end
$var reg 4 @ s_axi_wstrb [3:0] $end
$var reg 1 A s_axi_wvalid $end
$var reg 161 B step [160:0] $end
$var reg 1 C write_done $end
$var reg 1 D write_error $end
$scope module uut $end
$var wire 1 . read $end
$var wire 32 E read_data [31:0] $end
$var wire 1 3 read_done $end
$var wire 1 4 read_error $end
$var wire 1 5 s_axi_aclk $end
$var wire 4 F s_axi_araddr [3:0] $end
$var wire 1 7 s_axi_aresetn $end
$var wire 3 G s_axi_arprot [2:0] $end
$var wire 1 , s_axi_arready $end
$var wire 1 9 s_axi_arvalid $end
$var wire 4 H s_axi_awaddr [3:0] $end
$var wire 3 I s_axi_awprot [2:0] $end
$var wire 1 + s_axi_awready $end
$var wire 1 < s_axi_awvalid $end
$var wire 1 = s_axi_bready $end
$var wire 1 ) s_axi_bvalid $end
$var wire 1 > s_axi_rready $end
$var wire 1 & s_axi_rvalid $end
$var wire 32 J s_axi_wdata [31:0] $end
$var wire 1 % s_axi_wready $end
$var wire 4 K s_axi_wstrb [3:0] $end
$var wire 1 A s_axi_wvalid $end
$var wire 1 $ write $end
$var wire 1 C write_done $end
$var wire 1 D write_error $end
$var wire 4 L write_strobe [3:0] $end
$var wire 32 M write_data [31:0] $end
$var wire 6 N write_addrs [5:0] $end
$var wire 2 O s_axi_rresp [1:0] $end
$var wire 32 P s_axi_rdata [31:0] $end
$var wire 2 Q s_axi_bresp [1:0] $end
$var wire 6 R read_addrs [5:0] $end
$var parameter 6 S ADDR_MASK $end
$var parameter 32 T C_S_AXI_ADDR_WIDTH $end
$var parameter 32 U C_S_AXI_DATA_WIDTH $end
$var parameter 32 V GP_ADDR_WIDTH $end
$var parameter 2 W RES_ERR $end
$var parameter 2 X RES_OKAY $end
$var reg 1 Y got_read_addrs $end
$var reg 1 Z got_write_addrs $end
$var reg 1 [ got_write_data $end
$var reg 1 \ hold_read_resp $end
$var reg 1 ] hold_write_resp $end
$var reg 6 ^ read_addrs_hold [5:0] $end
$var reg 1 _ s_axi_bresp_hold $end
$var reg 32 ` s_axi_rdata_hold [31:0] $end
$var reg 1 a s_axi_rresp_hold $end
$var reg 6 b write_addrs_hold [5:0] $end
$var reg 32 c write_data_hold [31:0] $end
$var reg 4 d write_strobe_hold [3:0] $end
$upscope $end
$upscope $end
$enddefinitions $end
$comment Show the parameter values. $end
$dumpall
b0 X
b10 W
b110 V
b100000 U
b100 T
b111111 S
b110 1
b100000 0
b100 /
$end
#0
$dumpvars
bx d
bx c
bx b
xa
bx `
x_
bx ^
x]
x\
x[
xZ
xY
bx R
bx0 Q
bx P
bx0 O
bx N
bx M
bx L
b1111 K
b10010001101000101011001111000 J
b0 I
b100 H
b0 G
b101 F
b10111010101110100001000110010101 E
0D
0C
b1001001011011100110100101110100 B
0A
b1111 @
b10010001101000101011001111000 ?
0>
0=
0<
b0 ;
b100 :
09
b0 8
17
b101 6
05
04
03
b10111010101110100001000110010101 2
x.
bx -
x,
x+
bx0 *
x)
bx (
bx0 '
x&
x%
x$
bx #
bx "
bx !
$end
#1000
07
#5000
0$
1%
1+
0.
1,
b1111 !
b1111 L
b10010001101000101011001111000 "
b10010001101000101011001111000 M
b100 #
b100 N
b101 -
b101 R
b0 *
b0 Q
0)
b0 '
b0 O
0&
b10111010101110100001000110010101 (
b10111010101110100001000110010101 P
0[
0Z
0Y
0]
0\
b10111010101110100001000110010101 `
15
#6000
17
#10000
05
#15000
0a
0_
b10010001101000101011001111000 c
b1111 d
b101 ^
b100 b
15
#16000
13
1C
1>
1=
b1000010011011110111010001101000001000000101001001100101011000010110010001111001 B
#20000
05
#25000
15
#26000
1)
1&
1$
1.
1A
19
1<
#30000
05
#35000
15
#36000
0)
0&
0$
0.
0A
09
0<
#40000
05
#45000
15
#50000
05
#55000
15
#56000
b11011110101011011011111011101111 "
b11011110101011011011111011101111 M
b11011110101011011011111011101111 (
b11011110101011011011111011101111 P
b11011110101011011011111011101111 ?
b11011110101011011011111011101111 J
b11011110101011011011111011101111 2
b11011110101011011011111011101111 E
03
0C
b1000111010100000010000001010111011000010110100101110100011100110010000000110001001000000110001101111001011000110110110001100101 B
#60000
05
#65000
b11011110101011011011111011101111 c
b11011110101011011011111011101111 `
15
#66000
1$
1.
1A
19
1<
#70000
05
#75000
0,
0+
0%
1Y
1Z
1[
15
#76000
1&
1)
0A
09
0<
13
1C
#80000
05
#85000
0)
0&
0$
1%
1+
0.
1,
0[
0Z
0Y
15
#90000
05
#95000
15
#96000
b1110000100011110 "
b1110000100011110 M
b1110000100011110 (
b1110000100011110 P
b1110000100011110 ?
b1110000100011110 J
b1110000100011110 2
b1110000100011110 E
03
0C
b100011101010000001000000101011101100001011010010111010001110011001000000011001000100000011000110111100101100011011011000110010101110011 B
#100000
05
#105000
b1110000100011110 c
b1110000100011110 `
15
#106000
1$
1.
1A
19
1<
#110000
05
#115000
0,
0+
0%
1Y
1Z
1[
15
#116000
0A
09
0<
#120000
05
#125000
15
#126000
1&
1)
13
1C
#130000
05
#135000
0)
0&
0$
0.
1,
1+
1%
0Y
0Z
0[
15
#140000
05
#145000
15
#146000
b10010001101000101011001111000 "
b10010001101000101011001111000 M
b10010001101000101011001111000 (
b10010001101000101011001111000 P
b10010001101000101011001111000 ?
b10010001101000101011001111000 J
b10010001101000101011001111000 2
b10010001101000101011001111000 E
b100000101011000010010010010000001010111011000010110100101110100011100110010000000110001001000000110001101111001011000110110110001100101 B
#150000
05
#155000
b10010001101000101011001111000 `
b10010001101000101011001111000 c
15
#156000
1)
1&
1$
1.
0>
0=
1A
19
1<
#160000
05
#165000
0$
0%
0+
0.
0,
1]
1\
15
#166000
1>
1=
0A
09
0<
#170000
05
#175000
1,
1%
1+
0&
0)
0\
0]
15
#180000
05
#185000
15
#186000
b100010000001000001000110010101 "
b100010000001000001000110010101 M
b100010000001000001000110010101 (
b100010000001000001000110010101 P
b100010000001000001000110010101 ?
b100010000001000001000110010101 J
b100010000001000001000110010101 2
b100010000001000001000110010101 E
b10000010101100001001001001000000101011101100001011010010111010001110011001000000011001000100000011000110111100101100011011011000110010101110011 B
#190000
05
#195000
b100010000001000001000110010101 `
b100010000001000001000110010101 c
15
#196000
1)
1&
1$
1.
0>
0=
1A
19
1<
#200000
05
#205000
0$
0%
0+
0.
0,
1]
1\
15
#206000
0A
09
0<
#210000
05
#215000
15
#216000
1>
1=
#220000
05
#225000
1%
1+
1,
0)
0&
0]
0\
15
#230000
05
#235000
15
#236000
b1110000100011110 "
b1110000100011110 M
b0 (
b0 P
b1110000100011110 ?
b1110000100011110 J
b0 2
b0 E
03
0C
b1000111010100000010000001010111011000010110100101110100011100110010000001000100011000010111010001100001001000000110001101101000 B
#240000
05
#245000
b1110000100011110 c
b0 `
15
#246000
1$
1.
1A
19
1<
#250000
05
#255000
0,
0+
0%
1Y
1Z
1[
15
#256000
b0 6
b0 F
b0 ?
b0 J
0A
09
0<
#260000
05
#265000
15
#266000
1&
1)
b1110000100011110 (
b1110000100011110 P
13
1C
b1110000100011110 2
b1110000100011110 E
#270000
05
#275000
0)
0&
0$
0.
1,
1+
1%
b0 -
b0 R
b0 "
b0 M
b1110000100011110 `
0Y
0Z
0[
15
#280000
05
#285000
b0 c
b0 ^
15
#286000
b11 -
b11 R
b100010000001000001000110010101 "
b100010000001000001000110010101 M
b100010000001000001000110010101 (
b100010000001000001000110010101 P
b11 6
b11 F
b100010000001000001000110010101 ?
b100010000001000001000110010101 J
b100010000001000001000110010101 2
b100010000001000001000110010101 E
b100000101011000010010010010000001010111011000010110100101110100011100110010000001000100011000010111010001100001001000000110001101101000 B
#290000
05
#295000
b100010000001000001000110010101 `
b100010000001000001000110010101 c
b11 ^
15
#296000
1)
1&
1$
1.
0>
0=
1A
19
1<
#300000
05
#305000
0$
0%
0+
0.
0,
1]
1\
15
#306000
b0 -
b0 R
b0 "
b0 M
b0 6
b0 F
b0 ?
b0 J
b0 2
b0 E
0A
09
0<
#310000
05
#315000
b0 (
b0 P
b0 `
b0 c
b0 ^
15
#316000
1>
1=
#320000
05
#325000
1%
1+
1,
0)
0&
0]
0\
15
