examples/arreay_bug/rtl/fifo.sv
module fifo #(parameter DATA_WIDTH = 8, parameter DEPTH = 16)(
    input  wire                   clk,
    input  wire                   rst,
    input  wire                   wr_en,
    input  wire                   rd_en,
    input  wire [DATA_WIDTH-1:0] din,
    output reg  [DATA_WIDTH-1:0] dout,
    output reg                   full,
    output reg                   empty,
    output wire [4:0]            count
);

    // Calculate pointer width based on DEPTH
    localparam PTR_WIDTH = $clog2(DEPTH);

    // FIFO memory and control signals
    reg [DATA_WIDTH-1:0] mem [0:DEPTH-1];      // FIFO storage array
    reg [PTR_WIDTH-1:0]  wr_ptr, rd_ptr;       // Write and read pointers
    reg [PTR_WIDTH:0]    count_internal;       // Tracks number of valid entries
    reg                  reset_sync;           // Synchronous reset flag for assertions

    // Output assignments
    assign count = count_internal;
    assign dout  = mem[rd_ptr];

    // Delay write enable to detect next-cycle effects
    reg wr_en_d;
    always @(posedge clk) begin
        wr_en_d <= wr_en;
    end

    // Assertion: FIFO became full in the cycle after a write
    always @(posedge clk) begin
        if (!reset_sync) begin
            if (wr_en_d && full) begin
                $error("FIFO became full in the cycle after write");
            end
        end
    end

    // Assertion: Underflow — read attempted when FIFO is empty
    always @(posedge clk) begin
        if (!reset_sync) begin
            if (rd_en && (count_internal == 0)) begin
                $error("FIFO underflow: read attempted when empty");
            end
        end
    end

    // Assertion: Defensive check — count must not exceed DEPTH
    always @(posedge clk) begin
        if (!reset_sync) begin
            if (count_internal > DEPTH) begin
                $error("FIFO count exceeded DEPTH");
            end
        end
    end

    // FIFO logic with asynchronous reset
    always @(posedge clk or posedge rst) begin
        if (rst) begin
            // Reset all internal state
            wr_ptr        <= 0;
            rd_ptr        <= 0;
            count_internal <= 0;
            full          <= 0;
            empty         <= 1;
            reset_sync    <= 1;  // Enable assertion masking during reset
        end else begin
            reset_sync <= 0;     // Enable assertions after reset deasserts

            // Write operation: only if FIFO is not full
            if (wr_en && !full) begin
                mem[wr_ptr]     <= din;
                wr_ptr          <= wr_ptr + 1;
                count_internal  <= count_internal + 1;
            end

            // Read operation: only if FIFO is not empty
            if (rd_en && !empty) begin
                rd_ptr          <= rd_ptr + 1;
                count_internal  <= count_internal - 1;
            end

            // Update status flags
            full  <= (count_internal == DEPTH);
            empty <= (count_internal == 0);
        end
    end

endmodule

examples/arreay_bug/rtl/axi_lite_fifo_wrapper.sv
module axi_lite_fifo_wrapper #(
    parameter DATA_WIDTH = 8,
    parameter DEPTH      = 16
)(
    //=======================
    // AXI-Lite Global Signals
    //=======================
    input  wire                  ACLK,
    input  wire                  ARESETn,

    //=======================
    // AXI-Lite Write Address Channel
    input  wire [31:0]           AWADDR,
    input  wire                  AWVALID,
    output reg                   AWREADY,

    //=======================
    // AXI-Lite Write Data Channel
    input  wire [31:0]           WDATA,
    input  wire                  WVALID,
    output reg                   WREADY,

    //=======================
    // AXI-Lite Write Response Channel
    output reg [1:0]             BRESP,
    output reg                   BVALID,
    input  wire                  BREADY,

    //=======================
    // AXI-Lite Read Address Channel
    input  wire [31:0]           ARADDR,
    input  wire                  ARVALID,
    output reg                   ARREADY,

    //=======================
    // AXI-Lite Read Data Channel
    output reg [31:0]            RDATA,
    output reg [1:0]             RRESP,
    output reg                   RVALID,
    input  wire                  RREADY,

    //=======================
    // FIFO Status Output
    output wire [4:0]            fifo_level
);

    //============================================================
    // Dummy usage to silence Verilator warnings
    //============================================================
    wire unused_awaddr_bits = |AWADDR[31:4];
    wire unused_wdata_bits  = |WDATA[31:8];
    wire unused_araddr_bits = |ARADDR[31:4];

    //============================================================
    // Internal control signals
    //============================================================
    reg wr_en, rd_en;
    wire [DATA_WIDTH-1:0] dout;
    wire full, empty;
    wire [4:0] count;

    //============================================================
    // FIFO Instantiation
    //============================================================
    fifo #(.DATA_WIDTH(DATA_WIDTH), .DEPTH(DEPTH)) u_fifo (
        .clk   (ACLK),
        .rst   (~ARESETn),
        .wr_en (wr_en),
        .rd_en (rd_en),
        .din   (WDATA[DATA_WIDTH-1:0]),
        .dout  (dout),
        .full  (full),
        .empty (empty),
        .count (count)
    );

    assign fifo_level = count;

    //============================================================
    // FSM State Encoding
    //============================================================
    reg [1:0] write_state, read_state;
    localparam IDLE = 2'b00, RESP = 2'b01;

    //============================================================
    // AXI-Lite Write FSM
    //============================================================
    always @(posedge ACLK) begin
        if (!ARESETn) begin
            AWREADY     <= 0;
            WREADY      <= 0;
            BVALID      <= 0;
            BRESP       <= 2'b00;
            wr_en       <= 0;
            write_state <= IDLE;
        end else begin  
            wr_en <= 0;

            case (write_state)
                IDLE: begin
                  

                    if (AWVALID && WVALID) begin
                        // $display("[WRITE FSM] AWVALID && WVALID = %b at time %t", AWVALID && WVALID, $time);
                    AWREADY <= 1;
                    WREADY  <= 1;
                        if (AWADDR[3:0] == 4'h0 && !full) begin
                            // $display("[WRITE FSM] AWADDR = %h, full = %b", AWADDR, full);

                            wr_en  <= 1;
                            BRESP  <= 2'b00;  // OKAY
                        end else begin
                            BRESP  <= 2'b10;  // SLVERR
                        end
                        write_state <= RESP;
                    end
                    else begin
                    AWREADY <= 0;
                    WREADY  <= 0;
                    end
                end

                RESP: begin
                    AWREADY <= 0;
                    WREADY  <= 0;
                    BVALID  <= 1;

                    // $display("[WRITE FSM] BVALID asserted at time %t,BVALID = ", $time,BVALID);

                    if (BREADY) begin
                        BVALID      <= 0;
                        // $display("[WRITE FSM] BVALID asserted at time %t,BVALID = ", $time,BVALID); 
                        write_state <= IDLE;
                    end
                end

                default: begin
                    AWREADY     <= 0;
                    WREADY      <= 0;
                    BVALID      <= 0;
                    BRESP       <= 2'b10;
                    wr_en       <= 0;
                    write_state <= IDLE;
                end
            endcase
        end
    end
//============================================================
// AXI-Lite Read FSM
//============================================================
always @(posedge ACLK) begin
    if (!ARESETn) begin
        ARREADY    <= 0;
        RVALID     <= 0;
        RDATA      <= 0;
        RRESP      <= 2'b00;
        rd_en      <= 0;
        read_state <= IDLE;
    end else begin
        rd_en <= 0;

        case (read_state)
            IDLE: begin
                if (ARVALID) begin
                    ARREADY    <= 1;      // ✔ intended handshake
                    read_state <= RESP;

                    case (ARADDR[7:0])
                        8'h10: begin
                            if (!empty) begin
                                rd_en  <= 1;
                                RDATA  <= {24'b0, dout};
                                RRESP  <= 2'b00;
                            end else begin
                                RDATA  <= 32'hDEAD_BEEF;
                                RRESP  <= 2'b10;
                            end
                        end

                        8'h20: begin
                            RDATA <= {25'b0, count, full, empty};
                            RRESP <= 2'b00;
                        end

                        8'h80: begin
                            RDATA <= {27'b0, fifo_level};
                            RRESP <= 2'b00;
                        end

                        default: begin
                            RDATA <= 32'hBAD0BAD0;
                            RRESP <= 2'b11;
                        end
                    endcase
                end

                //BUG: accidental overwrite
                ARREADY <= 0;   // overwrites the correct assignment above
            end

            RESP: begin
                ARREADY <= 0;
                RVALID  <= 1;

                if (RREADY) begin
                    RVALID     <= 0;
                    read_state <= IDLE;
                end
            end

            default: begin
                ARREADY    <= 0;
                RVALID     <= 0;
                RDATA      <= 32'hBAD0BAD0;
                RRESP      <= 2'b11;
                rd_en      <= 0;
                read_state <= IDLE;
            end
        endcase
    end
end
endmodule

examples/arreay_bug/rtl/dut.v
//============================================================
// Top-Level DUT Module
// Wraps an AXI-Lite FIFO interface and exposes fifo_level
//============================================================
module dut (
    //=======================
    // AXI-Lite Global Signals
    //=======================
    input  wire         ACLK,       // AXI clock
    input  wire         ARESETn,    // Active-low AXI reset

    //=======================
    // AXI-Lite Write Address Channel
    //=======================
    input  wire [31:0]  AWADDR,     // Write address
    input  wire         AWVALID,    // Write address valid
    output wire         AWREADY,    // Write address ready

    //=======================
    // AXI-Lite Write Data Channel
    //=======================
    input  wire [31:0]  WDATA,      // Write data
    input  wire         WVALID,     // Write data valid
    output wire         WREADY,     // Write data ready

    //=======================
    // AXI-Lite Write Response Channel
    //=======================
    output wire [1:0]   BRESP,      // Write response (OKAY, SLVERR, etc.)
    output wire         BVALID,     // Write response valid
    input  wire         BREADY,     // Write response ready

    //=======================
    // AXI-Lite Read Address Channel
    //=======================
    input  wire [31:0]  ARADDR,     // Read address
    input  wire         ARVALID,    // Read address valid
    output wire         ARREADY,    // Read address ready

    //=======================
    // AXI-Lite Read Data Channel
    //=======================
    output wire [31:0]  RDATA,      // Read data
    output wire [1:0]   RRESP,      // Read response (OKAY, SLVERR, etc.)
    output wire         RVALID,     // Read data valid
    input  wire         RREADY,     // Read data ready

    //=======================
    // FIFO Status Output
    //=======================
    output wire [4:0]   fifo_level  // Exposed FIFO occupancy level
);

    //============================================================
    // AXI-Lite FIFO Wrapper Instantiation
    // Connects all AXI-Lite channels and exposes fifo_level
    //============================================================
    axi_lite_fifo_wrapper #(
        .DATA_WIDTH(8),     // FIFO data width
        .DEPTH(16)          // FIFO depth (entries)
    ) u_axi_fifo (
        // Global signals
        .ACLK      (ACLK),
        .ARESETn   (ARESETn),

        // Write address channel
        .AWADDR    (AWADDR),
        .AWVALID   (AWVALID),
        .AWREADY   (AWREADY),

        // Write data channel
        .WDATA     (WDATA),
        .WVALID    (WVALID),
        .WREADY    (WREADY),

        // Write response channel
        .BRESP     (BRESP),
        .BVALID    (BVALID),
        .BREADY    (BREADY),

        // Read address channel
        .ARADDR    (ARADDR),
        .ARVALID   (ARVALID),
        .ARREADY   (ARREADY),

        // Read data channel
        .RDATA     (RDATA),
        .RRESP     (RRESP),
        .RVALID    (RVALID),
        .RREADY    (RREADY),

        // FIFO status output
        .fifo_level(fifo_level)  //Connected cleanly to top-level output
    );

endmodule

examples/arreay_bug/wave/wave.vcd
$version Generated by VerilatedVcd $end
$timescale 1ps $end
 $scope module TOP $end
  $var wire 1 < ACLK $end
  $var wire 1 = ARESETn $end
  $var wire 32 > AWADDR [31:0] $end
  $var wire 1 ? AWVALID $end
  $var wire 1 @ AWREADY $end
  $var wire 32 A WDATA [31:0] $end
  $var wire 1 B WVALID $end
  $var wire 1 C WREADY $end
  $var wire 2 D BRESP [1:0] $end
  $var wire 1 E BVALID $end
  $var wire 1 F BREADY $end
  $var wire 32 G ARADDR [31:0] $end
  $var wire 1 H ARVALID $end
  $var wire 1 I ARREADY $end
  $var wire 32 J RDATA [31:0] $end
  $var wire 2 K RRESP [1:0] $end
  $var wire 1 L RVALID $end
  $var wire 1 M RREADY $end
  $var wire 5 N fifo_level [4:0] $end
  $scope module dut $end
   $var wire 1 < ACLK $end
   $var wire 1 = ARESETn $end
   $var wire 32 > AWADDR [31:0] $end
   $var wire 1 ? AWVALID $end
   $var wire 1 @ AWREADY $end
   $var wire 32 A WDATA [31:0] $end
   $var wire 1 B WVALID $end
   $var wire 1 C WREADY $end
   $var wire 2 D BRESP [1:0] $end
   $var wire 1 E BVALID $end
   $var wire 1 F BREADY $end
   $var wire 32 G ARADDR [31:0] $end
   $var wire 1 H ARVALID $end
   $var wire 1 I ARREADY $end
   $var wire 32 J RDATA [31:0] $end
   $var wire 2 K RRESP [1:0] $end
   $var wire 1 L RVALID $end
   $var wire 1 M RREADY $end
   $var wire 5 N fifo_level [4:0] $end
   $scope module u_axi_fifo $end
    $var wire 32 W DATA_WIDTH [31:0] $end
    $var wire 32 X DEPTH [31:0] $end
    $var wire 1 < ACLK $end
    $var wire 1 = ARESETn $end
    $var wire 32 > AWADDR [31:0] $end
    $var wire 1 ? AWVALID $end
    $var wire 1 @ AWREADY $end
    $var wire 32 A WDATA [31:0] $end
    $var wire 1 B WVALID $end
    $var wire 1 C WREADY $end
    $var wire 2 D BRESP [1:0] $end
    $var wire 1 E BVALID $end
    $var wire 1 F BREADY $end
    $var wire 32 G ARADDR [31:0] $end
    $var wire 1 H ARVALID $end
    $var wire 1 I ARREADY $end
    $var wire 32 J RDATA [31:0] $end
    $var wire 2 K RRESP [1:0] $end
    $var wire 1 L RVALID $end
    $var wire 1 M RREADY $end
    $var wire 5 N fifo_level [4:0] $end
    $var wire 1 O unused_awaddr_bits $end
    $var wire 1 P unused_wdata_bits $end
    $var wire 1 Q unused_araddr_bits $end
    $var wire 1 # wr_en $end
    $var wire 1 $ rd_en $end
    $var wire 8 ' dout [7:0] $end
    $var wire 1 ( full $end
    $var wire 1 ) empty $end
    $var wire 5 * count [4:0] $end
    $var wire 2 % write_state [1:0] $end
    $var wire 2 & read_state [1:0] $end
    $var wire 2 Y IDLE [1:0] $end
    $var wire 2 Z RESP [1:0] $end
    $scope module u_fifo $end
     $var wire 32 W DATA_WIDTH [31:0] $end
     $var wire 32 X DEPTH [31:0] $end
     $var wire 1 < clk $end
     $var wire 1 R rst $end
     $var wire 1 # wr_en $end
     $var wire 1 $ rd_en $end
     $var wire 8 S din [7:0] $end
     $var wire 8 ' dout [7:0] $end
     $var wire 1 ( full $end
     $var wire 1 ) empty $end
     $var wire 5 * count [4:0] $end
     $var wire 32 [ PTR_WIDTH [31:0] $end
     $var wire 8 + mem[0] [7:0] $end
     $var wire 8 , mem[1] [7:0] $end
     $var wire 8 - mem[2] [7:0] $end
     $var wire 8 . mem[3] [7:0] $end
     $var wire 8 / mem[4] [7:0] $end
     $var wire 8 0 mem[5] [7:0] $end
     $var wire 8 1 mem[6] [7:0] $end
     $var wire 8 2 mem[7] [7:0] $end
     $var wire 8 3 mem[8] [7:0] $end
     $var wire 8 4 mem[9] [7:0] $end
     $var wire 8 5 mem[10] [7:0] $end
     $var wire 8 6 mem[11] [7:0] $end
     $var wire 8 7 mem[12] [7:0] $end
     $var wire 8 8 mem[13] [7:0] $end
     $var wire 8 9 mem[14] [7:0] $end
     $var wire 8 : mem[15] [7:0] $end
     $var wire 4 T wr_ptr [3:0] $end
     $var wire 4 ; rd_ptr [3:0] $end
     $var wire 5 * count_internal [4:0] $end
     $var wire 1 U reset_sync $end
     $var wire 1 V wr_en_d $end
    $upscope $end
   $upscope $end
  $upscope $end
 $upscope $end
$enddefinitions $end


#5
0#
0$
b00 %
b00 &
b00000000 '
0(
1)
b00000 *
b00000000 +
b00000000 ,
b00000000 -
b00000000 .
b00000000 /
b00000000 0
b00000000 1
b00000000 2
b00000000 3
b00000000 4
b00000000 5
b00000000 6
b00000000 7
b00000000 8
b00000000 9
b00000000 :
b0000 ;
1<
0=
b00000000000000000000000000000000 >
0?
0@
b00000000000000000000000000000000 A
0B
0C
b00 D
0E
0F
b00000000000000000000000000000000 G
0H
0I
b00000000000000000000000000000000 J
b00 K
0L
0M
b00000 N
0O
0P
0Q
1R
b00000000 S
b0000 T
1U
0V
b00000000000000000000000000001000 W
b00000000000000000000000000010000 X
b00 Y
b01 Z
b00000000000000000000000000000100 [
#10
0<
#15
1<
#20
0<
#25
1<
#30
0<
#35
1<
#40
0<
#45
1<
#50
0<
#55
1<
#60
0<
#65
1<
#70
0<
#75
1<
#80
0<
#85
1<
#90
0<
#95
1<
#100
0<
#105
1<
#110
0<
#115
1<
#120
0<
#125
1<
#130
0<
#135
1<
#140
0<
#145
1<
#150
0<
#155
1<
#160
0<
#165
1<
#170
0<
#175
1<
#180
0<
#185
1<
#190
0<
#195
1<
#200
0<
#205
1<
#210
0<
#215
1<
#220
0<
#225
1<
#230
0<
#235
1<
#240
0<
#245
1<
#250
0<
#255
1<
1=
0R
0U
#260
0<
#265
1<
#270
0<
#275
1<
#280
0<
#285
1#
b01 %
1<
1?
1@
b00000000000000000000000010100001 A
1B
1C
b10100001 S
#290
0<
#295
0#
b10100001 '
b00001 *
b10100001 +
1<
0?
0@
0B
0C
1E
b00001 N
b0001 T
1V
#300
0<
1F
#305
b00 %
0)
1<
0E
0V
#310
0<
0F
#315
1<
#320
0<
1?
b00000000000000000000000000000000 A
1B
b00000000 S
#325
1#
b01 %
1<
1@
1C
#330
0<
0?
0B
#335
0#
b00010 *
1<
0@
0C
1E
b00010 N
b0010 T
1V
#340
0<
1F
#345
b00 %
1<
0E
0V
#350
0<
0F
#355
1<
#360
0<
1?
b00000000000000000000000011000011 A
1B
b11000011 S
#365
1#
b01 %
1<
1@
1C
#370
0<
0?
0B
#375
0#
b00011 *
b11000011 -
1<
0@
0C
1E
b00011 N
b0011 T
1V
#380
0<
1F
#385
b00 %
1<
0E
0V
#390
0<
0F
#395
1<
#400
0<
1?
b00000000000000000000000010110011 A
1B
b10110011 S
#405
1#
b01 %
1<
1@
1C
#410
0<
0?
0B
#415
0#
b00100 *
b10110011 .
1<
0@
0C
1E
b00100 N
b0100 T
1V
#420
0<
1F
#425
b00 %
1<
0E
0V
#430
0<
0F
#435
1<
#440
0<
1?
b11111111111111111111111111111111 A
1B
1P
b11111111 S
#445
1#
b01 %
1<
1@
1C
#450
0<
0?
0B
#455
0#
b00101 *
b11111111 /
1<
0@
0C
1E
b00101 N
b0101 T
1V
#460
0<
1F
#465
b00 %
1<
0E
0V
#470
0<
0F
#475
1<
#480
0<
1?
1B
#485
1#
b01 %
1<
1@
1C
#490
0<
0?
0B
#495
0#
b00110 *
b11111111 0
1<
0@
0C
1E
b00110 N
b0110 T
1V
#500
0<
1F
#505
b00 %
1<
0E
0V
#510
0<
0F
#515
1<
#520
0<
1?
1B
#525
1#
b01 %
1<
1@
1C
#530
0<
0?
0B
#535
0#
b00111 *
b11111111 1
1<
0@
0C
1E
b00111 N
b0111 T
1V
#540
0<
1F
#545
b00 %
1<
0E
0V
#550
0<
0F
#555
1<
#560
0<
1?
1B
#565
1#
b01 %
1<
1@
1C
#570
0<
0?
0B
#575
0#
b01000 *
b11111111 2
1<
0@
0C
1E
b01000 N
b1000 T
1V
#580
0<
1F
#585
b00 %
1<
0E
0V
#590
0<
0F
#595
1<
#600
0<
1?
1B
#605
1#
b01 %
1<
1@
1C
#610
0<
0?
0B
#615
0#
b01001 *
b11111111 3
1<
0@
0C
1E
b01001 N
b1001 T
1V
#620
0<
1F
#625
b00 %
1<
0E
0V
#630
0<
0F
#635
1<
#640
0<
1?
1B
#645
1#
b01 %
1<
1@
1C
#650
0<
0?
0B
#655
0#
b01010 *
b11111111 4
1<
0@
0C
1E
b01010 N
b1010 T
1V
#660
0<
1F
#665
b00 %
1<
0E
0V
#670
0<
0F
#675
1<
#680
0<
1?
1B
#685
1#
b01 %
1<
1@
1C
#690
0<
0?
0B
#695
0#
b01011 *
b11111111 5
1<
0@
0C
1E
b01011 N
b1011 T
1V
#700
0<
1F
#705
b00 %
1<
0E
0V
#710
0<
0F
#715
1<
#720
0<
1?
1B
#725
1#
b01 %
1<
1@
1C
#730
0<
0?
0B
#735
0#
b01100 *
b11111111 6
1<
0@
0C
1E
b01100 N
b1100 T
1V
#740
0<
1F
#745
b00 %
1<
0E
0V
#750
0<
0F
#755
1<
#760
0<
1?
b11111111111111111111101111111111 A
1B
#765
1#
b01 %
1<
1@
1C
#770
0<
0?
0B
#775
0#
b01101 *
b11111111 7
1<
0@
0C
1E
b01101 N
b1101 T
1V
#780
0<
1F
#785
b00 %
1<
0E
0V
#790
0<
0F
#795
1<
#800
0<
1?
b11111111111111111111101011111111 A
1B
#805
1#
b01 %
1<
1@
1C
#810
0<
0?
0B
#815
0#
b01110 *
b11111111 8
1<
0@
0C
1E
b01110 N
b1110 T
1V
#820
0<
1F
#825
b00 %
1<
0E
0V
#830
0<
0F
#835
1<
#840
0<
1?
b11111111111111111111111011111111 A
1B
#845
1#
b01 %
1<
1@
1C
#850
0<
0?
0B
#855
0#
b01111 *
b11111111 9
1<
0@
0C
1E
b01111 N
b1111 T
1V
#860
0<
1F
#865
b00 %
1<
0E
0V
#870
0<
0F
#875
1<
#880
0<
1?
b11111111111111111111110011111111 A
1B
#885
1#
b01 %
1<
1@
1C
#890
0<
0?
0B
#895
0#
b10000 *
b11111111 :
1<
0@
0C
1E
b10000 N
b0000 T
1V
#900
0<
1F
#905
b00 %
1(
1<
0E
0V
#910
0<
0F
#915
1<
#920
0<
b00000000000000000000000000010000 G
1H
1Q
#925
1$
b01 &
1<
b00000000000000000000000010100001 J
#930
0<
#935
0$
b00000000 '
b01111 *
b0001 ;
1<
1L
b01111 N
#940
0<
#945
0(
1<
