examples/axil_dp_ram/rtl/axil_dp_ram.v
/*

Copyright (c) 2018 Alex Forencich

Permission is hereby granted, free of charge, to any person obtaining a copy
of this software and associated documentation files (the "Software"), to deal
in the Software without restriction, including without limitation the rights
to use, copy, modify, merge, publish, distribute, sublicense, and/or sell
copies of the Software, and to permit persons to whom the Software is
furnished to do so, subject to the following conditions:

The above copyright notice and this permission notice shall be included in
all copies or substantial portions of the Software.

THE SOFTWARE IS PROVIDED "AS IS", WITHOUT WARRANTY OF ANY KIND, EXPRESS OR
IMPLIED, INCLUDING BUT NOT LIMITED TO THE WARRANTIES OF MERCHANTABILITY
FITNESS FOR A PARTICULAR PURPOSE AND NONINFRINGEMENT. IN NO EVENT SHALL THE
AUTHORS OR COPYRIGHT HOLDERS BE LIABLE FOR ANY CLAIM, DAMAGES OR OTHER
LIABILITY, WHETHER IN AN ACTION OF CONTRACT, TORT OR OTHERWISE, ARISING FROM,
OUT OF OR IN CONNECTION WITH THE SOFTWARE OR THE USE OR OTHER DEALINGS IN
THE SOFTWARE.

*/

// Language: Verilog 2001

`resetall
`timescale 1ns / 1ps
`default_nettype none

/*
 * AXI4-Lite dual port RAM
 */
module axil_dp_ram #
(
    // Width of data bus in bits
    parameter DATA_WIDTH = 32,
    // Width of address bus in bits
    parameter ADDR_WIDTH = 16,
    // Width of wstrb (width of data bus in words)
    parameter STRB_WIDTH = (DATA_WIDTH/8),
    // Extra pipeline register on output
    parameter PIPELINE_OUTPUT = 0
)
(
    input  wire                   a_clk,
    input  wire                   a_rst,

    input  wire                   b_clk,
    input  wire                   b_rst,

    input  wire [ADDR_WIDTH-1:0]  s_axil_a_awaddr,
    input  wire [2:0]             s_axil_a_awprot,
    input  wire                   s_axil_a_awvalid,
    output wire                   s_axil_a_awready,
    input  wire [DATA_WIDTH-1:0]  s_axil_a_wdata,
    input  wire [STRB_WIDTH-1:0]  s_axil_a_wstrb,
    input  wire                   s_axil_a_wvalid,
    output wire                   s_axil_a_wready,
    output wire [1:0]             s_axil_a_bresp,
    output wire                   s_axil_a_bvalid,
    input  wire                   s_axil_a_bready,
    input  wire [ADDR_WIDTH-1:0]  s_axil_a_araddr,
    input  wire [2:0]             s_axil_a_arprot,
    input  wire                   s_axil_a_arvalid,
    output wire                   s_axil_a_arready,
    output wire [DATA_WIDTH-1:0]  s_axil_a_rdata,
    output wire [1:0]             s_axil_a_rresp,
    output wire                   s_axil_a_rvalid,
    input  wire                   s_axil_a_rready,

    input  wire [ADDR_WIDTH-1:0]  s_axil_b_awaddr,
    input  wire [2:0]             s_axil_b_awprot,
    input  wire                   s_axil_b_awvalid,
    output wire                   s_axil_b_awready,
    input  wire [DATA_WIDTH-1:0]  s_axil_b_wdata,
    input  wire [STRB_WIDTH-1:0]  s_axil_b_wstrb,
    input  wire                   s_axil_b_wvalid,
    output wire                   s_axil_b_wready,
    output wire [1:0]             s_axil_b_bresp,
    output wire                   s_axil_b_bvalid,
    input  wire                   s_axil_b_bready,
    input  wire [ADDR_WIDTH-1:0]  s_axil_b_araddr,
    input  wire [2:0]             s_axil_b_arprot,
    input  wire                   s_axil_b_arvalid,
    output wire                   s_axil_b_arready,
    output wire [DATA_WIDTH-1:0]  s_axil_b_rdata,
    output wire [1:0]             s_axil_b_rresp,
    output wire                   s_axil_b_rvalid,
    input  wire                   s_axil_b_rready
);

parameter VALID_ADDR_WIDTH = ADDR_WIDTH - $clog2(STRB_WIDTH);
parameter WORD_WIDTH = STRB_WIDTH;
parameter WORD_SIZE = DATA_WIDTH/WORD_WIDTH;

reg read_eligible_a;
reg write_eligible_a;

reg read_eligible_b;
reg write_eligible_b;

reg mem_wr_en_a;
reg mem_rd_en_a;

reg mem_wr_en_b;
reg mem_rd_en_b;

reg last_read_a_reg = 1'b0, last_read_a_next;
reg last_read_b_reg = 1'b0, last_read_b_next;

reg s_axil_a_awready_reg = 1'b0, s_axil_a_awready_next;
reg s_axil_a_wready_reg = 1'b0, s_axil_a_wready_next;
reg s_axil_a_bvalid_reg = 1'b0, s_axil_a_bvalid_next;
reg s_axil_a_arready_reg = 1'b0, s_axil_a_arready_next;
reg [DATA_WIDTH-1:0] s_axil_a_rdata_reg = {DATA_WIDTH{1'b0}}, s_axil_a_rdata_next;
reg s_axil_a_rvalid_reg = 1'b0, s_axil_a_rvalid_next;
reg [DATA_WIDTH-1:0] s_axil_a_rdata_pipe_reg = {DATA_WIDTH{1'b0}};
reg s_axil_a_rvalid_pipe_reg = 1'b0;

reg s_axil_b_awready_reg = 1'b0, s_axil_b_awready_next;
reg s_axil_b_wready_reg = 1'b0, s_axil_b_wready_next;
reg s_axil_b_bvalid_reg = 1'b0, s_axil_b_bvalid_next;
reg s_axil_b_arready_reg = 1'b0, s_axil_b_arready_next;
reg [DATA_WIDTH-1:0] s_axil_b_rdata_reg = {DATA_WIDTH{1'b0}}, s_axil_b_rdata_next;
reg s_axil_b_rvalid_reg = 1'b0, s_axil_b_rvalid_next;
reg [DATA_WIDTH-1:0] s_axil_b_rdata_pipe_reg = {DATA_WIDTH{1'b0}};
reg s_axil_b_rvalid_pipe_reg = 1'b0;

// (* RAM_STYLE="BLOCK" *)
reg [DATA_WIDTH-1:0] mem[(2**VALID_ADDR_WIDTH)-1:0];

wire [VALID_ADDR_WIDTH-1:0] s_axil_a_awaddr_valid = s_axil_a_awaddr >> (ADDR_WIDTH - VALID_ADDR_WIDTH);
wire [VALID_ADDR_WIDTH-1:0] s_axil_a_araddr_valid = s_axil_a_araddr >> (ADDR_WIDTH - VALID_ADDR_WIDTH);

wire [VALID_ADDR_WIDTH-1:0] s_axil_b_awaddr_valid = s_axil_b_awaddr >> (ADDR_WIDTH - VALID_ADDR_WIDTH);
wire [VALID_ADDR_WIDTH-1:0] s_axil_b_araddr_valid = s_axil_b_araddr >> (ADDR_WIDTH - VALID_ADDR_WIDTH);

assign s_axil_a_awready = s_axil_a_awready_reg;
assign s_axil_a_wready = s_axil_a_wready_reg;
assign s_axil_a_bresp = 2'b00;
assign s_axil_a_bvalid = s_axil_a_bvalid_reg;
assign s_axil_a_arready = s_axil_a_arready_reg;
assign s_axil_a_rdata = PIPELINE_OUTPUT ? s_axil_a_rdata_pipe_reg : s_axil_a_rdata_reg;
assign s_axil_a_rresp = 2'b00;
assign s_axil_a_rvalid = PIPELINE_OUTPUT ? s_axil_a_rvalid_pipe_reg : s_axil_a_rvalid_reg;

assign s_axil_b_awready = s_axil_b_awready_reg;
assign s_axil_b_wready = s_axil_b_wready_reg;
assign s_axil_b_bresp = 2'b00;
assign s_axil_b_bvalid = s_axil_b_bvalid_reg;
assign s_axil_b_arready = s_axil_b_arready_reg;
assign s_axil_b_rdata = PIPELINE_OUTPUT ? s_axil_b_rdata_pipe_reg : s_axil_b_rdata_reg;
assign s_axil_b_rresp = 2'b00;
assign s_axil_b_rvalid = PIPELINE_OUTPUT ? s_axil_b_rvalid_pipe_reg : s_axil_b_rvalid_reg;

integer i, j;

initial begin
    // two nested loops for smaller number of iterations per loop
    // workaround for synthesizer complaints about large loop counts
    for (i = 0; i < 2**VALID_ADDR_WIDTH; i = i + 2**(VALID_ADDR_WIDTH/2)) begin
        for (j = i; j < i + 2**(VALID_ADDR_WIDTH/2); j = j + 1) begin
            mem[j] = 0;
        end
    end
end

always @* begin
    mem_wr_en_a = 1'b0;
    mem_rd_en_a = 1'b0;

    last_read_a_next = last_read_a_reg;

    s_axil_a_awready_next = 1'b0;
    s_axil_a_wready_next = 1'b0;
    s_axil_a_bvalid_next = s_axil_a_bvalid_reg && !s_axil_a_bready;

    s_axil_a_arready_next = 1'b0;
    s_axil_a_rvalid_next = s_axil_a_rvalid_reg && !(s_axil_a_rready || (PIPELINE_OUTPUT && !s_axil_a_rvalid_pipe_reg));

    write_eligible_a = s_axil_a_awvalid && s_axil_a_wvalid && (!s_axil_a_bvalid || s_axil_a_bready) && (!s_axil_a_awready && !s_axil_a_wready);
    read_eligible_a = s_axil_a_arvalid && (!s_axil_a_rvalid || s_axil_a_rready || (PIPELINE_OUTPUT && !s_axil_a_rvalid_pipe_reg)) && (!s_axil_a_arready);

    if (write_eligible_a && (!read_eligible_a || last_read_a_reg)) begin
        last_read_a_next = 1'b0;

        s_axil_a_awready_next = 1'b1;
        s_axil_a_wready_next = 1'b1;
        s_axil_a_bvalid_next = 1'b1;

        mem_wr_en_a = 1'b1;
    end else if (read_eligible_a) begin
        last_read_a_next = 1'b1;

        s_axil_a_arready_next = 1'b1;
        s_axil_a_rvalid_next = 1'b1;

        mem_rd_en_a = 1'b1;
    end
end

always @(posedge a_clk) begin
    last_read_a_reg <= last_read_a_next;

    s_axil_a_awready_reg <= s_axil_a_awready_next;
    s_axil_a_wready_reg <= s_axil_a_wready_next;
    s_axil_a_bvalid_reg <= s_axil_a_bvalid_next;

    s_axil_a_arready_reg <= s_axil_a_arready_next;
    s_axil_a_rvalid_reg <= s_axil_a_rvalid_next;

    if (mem_rd_en_a) begin
        s_axil_a_rdata_reg <= mem[s_axil_a_araddr_valid];
    end else begin
        for (i = 0; i < WORD_WIDTH; i = i + 1) begin
            if (mem_wr_en_a && s_axil_a_wstrb[i]) begin
                mem[s_axil_a_awaddr_valid][WORD_SIZE*i +: WORD_SIZE] <= s_axil_a_wdata[WORD_SIZE*i +: WORD_SIZE];
            end
        end
    end

    if (!s_axil_a_rvalid_pipe_reg || s_axil_a_rready) begin
        s_axil_a_rdata_pipe_reg <= s_axil_a_rdata_reg;
        s_axil_a_rvalid_pipe_reg <= s_axil_a_rvalid_reg;
    end

    if (a_rst) begin
        last_read_a_reg <= 1'b0;

        s_axil_a_awready_reg <= 1'b0;
        s_axil_a_wready_reg <= 1'b0;
        s_axil_a_bvalid_reg <= 1'b0;

        s_axil_a_arready_reg <= 1'b0;
        s_axil_a_rvalid_reg <= 1'b0;
        s_axil_a_rvalid_pipe_reg <= 1'b0;
    end
end

always @* begin
    mem_wr_en_b = 1'b0;
    mem_rd_en_b = 1'b0;

    last_read_b_next = last_read_b_reg;

    s_axil_b_awready_next = 1'b0;
    s_axil_b_wready_next = 1'b0;
    s_axil_b_bvalid_next = s_axil_b_bvalid_reg && !s_axil_b_bready;

    s_axil_b_arready_next = 1'b0;
    s_axil_b_rvalid_next = s_axil_b_rvalid_reg && !(s_axil_b_rready || (PIPELINE_OUTPUT && !s_axil_b_rvalid_pipe_reg));

    write_eligible_b = s_axil_b_awvalid && s_axil_b_wvalid && (!s_axil_b_bvalid || s_axil_b_bready) && (!s_axil_b_awready && !s_axil_b_wready);
    read_eligible_b = s_axil_b_arvalid && (!s_axil_b_rvalid || s_axil_b_rready || (PIPELINE_OUTPUT && !s_axil_b_rvalid_pipe_reg)) && (!s_axil_b_arready);

    if (write_eligible_b && (!read_eligible_b || last_read_b_reg)) begin
        last_read_b_next = 1'b0;

        s_axil_b_awready_next = 1'b1;
        s_axil_b_wready_next = 1'b1;
        s_axil_b_bvalid_next = 1'b1;

        mem_wr_en_b = 1'b1;
    end else if (read_eligible_b) begin
        last_read_b_next = 1'b1;

        s_axil_b_arready_next = 1'b1;
        s_axil_b_rvalid_next = 1'b1;

        mem_rd_en_b = 1'b1;
    end
end

always @(posedge b_clk) begin
        last_read_b_reg <= last_read_b_next;

    s_axil_b_awready_reg <= s_axil_b_awready_next;
    s_axil_b_wready_reg <= s_axil_b_wready_next;
    s_axil_b_bvalid_reg <= s_axil_b_bvalid_next;

    s_axil_b_arready_reg <= s_axil_b_arready_next;
    s_axil_b_rvalid_reg <= s_axil_b_rvalid_next;

    if (mem_rd_en_b) begin
        s_axil_b_rdata_reg <= mem[s_axil_b_araddr_valid];
    end else begin
    // BUG: Port B writes collapse all strobed bytes into lane 0
    // Port A remains correct, creating cross-port incoherency
    for (i = 0; i < WORD_WIDTH; i = i + 1) begin
        if (mem_wr_en_b && s_axil_b_wstrb[i]) begin
            mem[s_axil_b_awaddr_valid][0 +: WORD_SIZE] <=
                s_axil_b_wdata[WORD_SIZE*i +: WORD_SIZE];
        end
    end
    end

    if (!s_axil_b_rvalid_pipe_reg || s_axil_b_rready) begin
        s_axil_b_rdata_pipe_reg <= s_axil_b_rdata_reg;
        s_axil_b_rvalid_pipe_reg <= s_axil_b_rvalid_reg;
    end

    if (b_rst) begin
        last_read_b_reg <= 1'b0;

        s_axil_b_awready_reg <= 1'b0;
        s_axil_b_wready_reg <= 1'b0;
        s_axil_b_bvalid_reg <= 1'b0;

        s_axil_b_arready_reg <= 1'b0;
        s_axil_b_rvalid_reg <= 1'b0;
        s_axil_b_rvalid_pipe_reg <= 1'b0;
    end
end

endmodule

`resetall

examples/axil_dp_ram/wave/axil_dp_ram.vcd
$date
	Wed Feb 25 17:34:41 2026
$end
$version
	GTKWave Analyzer v3.3.100 (w)1999-2019 BSI
$end
$timescale
	1ps
$end
$scope module axil_dp_ram $end
$var wire 1 ) a_clk $end
$var wire 1 * a_rst $end
$var wire 1 + b_clk $end
$var wire 1 , b_rst $end
$var wire 16 9 s_axil_a_araddr[15:0] $end
$var wire 3 ; s_axil_a_arprot[2:0] $end
$var wire 1 < s_axil_a_arready $end
$var wire 1 ? s_axil_a_arvalid $end
$var wire 16 @ s_axil_a_awaddr[15:0] $end
$var wire 3 B s_axil_a_awprot[2:0] $end
$var wire 1 C s_axil_a_awready $end
$var wire 1 F s_axil_a_awvalid $end
$var wire 1 G s_axil_a_bready $end
$var wire 2 H s_axil_a_bresp[1:0] $end
$var wire 1 I s_axil_a_bvalid $end
$var wire 32 L s_axil_a_rdata[31:0] $end
$var wire 1 O s_axil_a_rready $end
$var wire 2 P s_axil_a_rresp[1:0] $end
$var wire 1 Q s_axil_a_rvalid $end
$var wire 32 U s_axil_a_wdata[31:0] $end
$var wire 1 V s_axil_a_wready $end
$var wire 4 Y s_axil_a_wstrb[3:0] $end
$var wire 1 Z s_axil_a_wvalid $end
$var wire 16 [ s_axil_b_araddr[15:0] $end
$var wire 3 ] s_axil_b_arprot[2:0] $end
$var wire 1 ^ s_axil_b_arready $end
$var wire 1 a s_axil_b_arvalid $end
$var wire 16 b s_axil_b_awaddr[15:0] $end
$var wire 3 d s_axil_b_awprot[2:0] $end
$var wire 1 e s_axil_b_awready $end
$var wire 1 h s_axil_b_awvalid $end
$var wire 1 i s_axil_b_bready $end
$var wire 2 j s_axil_b_bresp[1:0] $end
$var wire 1 k s_axil_b_bvalid $end
$var wire 32 n s_axil_b_rdata[31:0] $end
$var wire 1 q s_axil_b_rready $end
$var wire 2 r s_axil_b_rresp[1:0] $end
$var wire 1 s s_axil_b_rvalid $end
$var wire 32 w s_axil_b_wdata[31:0] $end
$var wire 1 x s_axil_b_wready $end
$var wire 4 { s_axil_b_wstrb[3:0] $end
$var wire 1 | s_axil_b_wvalid $end
$var wire 14 c s_axil_b_awaddr_valid[13:0] $end
$var wire 14 \ s_axil_b_araddr_valid[13:0] $end
$var wire 14 A s_axil_a_awaddr_valid[13:0] $end
$var wire 14 : s_axil_a_araddr_valid[13:0] $end
$var wire 32 " ADDR_WIDTH $end
$var wire 32 # DATA_WIDTH $end
$var wire 32 $ PIPELINE_OUTPUT $end
$var wire 32 % STRB_WIDTH $end
$var wire 33 & VALID_ADDR_WIDTH $end
$var wire 32 ' WORD_SIZE $end
$var wire 32 ( WORD_WIDTH $end
$var wire 1 / last_read_a_next $end
$var wire 1 0 last_read_a_reg $end
$var wire 1 1 last_read_b_next $end
$var wire 1 2 last_read_b_reg $end
$var wire 1 3 mem_rd_en_a $end
$var wire 1 4 mem_rd_en_b $end
$var wire 1 5 mem_wr_en_a $end
$var wire 1 6 mem_wr_en_b $end
$var wire 1 7 read_eligible_a $end
$var wire 1 8 read_eligible_b $end
$var wire 1 = s_axil_a_arready_next $end
$var wire 1 > s_axil_a_arready_reg $end
$var wire 1 D s_axil_a_awready_next $end
$var wire 1 E s_axil_a_awready_reg $end
$var wire 1 J s_axil_a_bvalid_next $end
$var wire 1 K s_axil_a_bvalid_reg $end
$var wire 32 M s_axil_a_rdata_pipe_reg[31:0] $end
$var wire 32 N s_axil_a_rdata_reg[31:0] $end
$var wire 1 R s_axil_a_rvalid_next $end
$var wire 1 S s_axil_a_rvalid_pipe_reg $end
$var wire 1 T s_axil_a_rvalid_reg $end
$var wire 1 W s_axil_a_wready_next $end
$var wire 1 X s_axil_a_wready_reg $end
$var wire 1 _ s_axil_b_arready_next $end
$var wire 1 ` s_axil_b_arready_reg $end
$var wire 1 f s_axil_b_awready_next $end
$var wire 1 g s_axil_b_awready_reg $end
$var wire 1 l s_axil_b_bvalid_next $end
$var wire 1 m s_axil_b_bvalid_reg $end
$var wire 32 o s_axil_b_rdata_pipe_reg[31:0] $end
$var wire 32 p s_axil_b_rdata_reg[31:0] $end
$var wire 1 t s_axil_b_rvalid_next $end
$var wire 1 u s_axil_b_rvalid_pipe_reg $end
$var wire 1 v s_axil_b_rvalid_reg $end
$var wire 1 y s_axil_b_wready_next $end
$var wire 1 z s_axil_b_wready_reg $end
$var wire 1 } write_eligible_a $end
$var wire 1 ~ write_eligible_b $end
$var wire 32 - i $end
$var wire 32 . j $end
$upscope $end
$enddefinitions $end
$dumpvars
#0
0e
bx A
0s
b0 j
1)
bx w
08
b100000000000000 .
0,
0K
0=
0>
0?
0*
1i
0D
b0 L
0J
b0 r
b0 n
1O
0k
0E
b0 N
0_
0R
0S
bx @
b0 M
1q
0T
b0 P
0X
0z
bx {
0`
b100 -
0W
0Q
bx 9
0t
0g
0l
bx B
0f
0x
0m
bx U
b0 p
0}
bx c
0V
0|
b0 o
0v
bx :
0y
0Z
0C
0u
bx \
bx Y
0I
b1000 '
1+
0a
0~
07
b10000 "
b0 $
bx ;
b100 %
bx [
b100000 #
0F
bx ]
b100 (
b1110 &
05
00
0h
1G
0^
0/
02
0<
03
bx b
01
b0 H
bx d
06
04
#4000
0)
#5000
0+
#8000
0i
1*
1,
0q
0O
1)
0G
#10000
1+
#12000
0)
#15000
0+
#16000
1)
#20000
0)
1+
#24000
0*
1)
#25000
0+
#28000
0)
#30000
1+
0,
#32000
1)
1G
1O
#35000
0+
#36000
0)
#40000
1)
1+
1q
1i
#44000
0)
#45000
0+
#48000
1)
b1111111111 A
1J
1D
b111111111100 @
1W
b10 B
b10101010101010101010101010101010 U
1}
1Z
b1111 Y
1F
15
#50000
1+
#52000
0)
#55000
0+
#56000
1)
05
1K
0}
0J
1E
0D
1X
1C
1V
0W
1I
#60000
1+
0)
#64000
1)
0I
1}
0V
b10000000000 A
0K
15
0C
1J
0X
0E
b1000000000000 @
1D
1W
#65000
0+
#68000
0)
#70000
1+
#72000
1)
0W
1V
0}
1I
1E
1K
1X
1C
05
0J
0D
#75000
0+
#76000
0)
#80000
1)
1+
1D
b10000000001 A
15
b1000000000100 @
0V
1W
0C
1}
b10101010 U
0X
0E
0I
0K
1J
b1 Y
#84000
0)
#85000
0+
#88000
1)
1I
05
0D
1E
0W
1V
1X
0}
1C
0J
1K
#90000
1+
#92000
0)
#95000
0+
#96000
1)
0K
0I
0X
0V
0E
0F
0Z
0C
#100000
0)
1+
#104000
1)
b1000000000000 @
1}
b10000000000 A
1D
15
1W
b0 U
1Z
1J
1F
#105000
0+
#108000
0)
#110000
1+
#112000
1)
1C
0W
1V
05
0}
1X
0D
1I
1K
0J
1E
#115000
0+
#116000
0)
#120000
1)
1+
0E
0F
0I
0C
0V
0X
0K
0Z
#124000
0)
#125000
0+
#128000
1)
1?
1=
1R
b111111111111 9
b1111111111 :
17
b10 ;
1/
13
#130000
1+
#132000
0)
#135000
0+
#136000
1)
03
1T
1>
b10101010101010101010101010101010 L
b10101010101010101010101010101010 N
0R
1Q
0=
10
07
1<
#140000
0)
1+
#144000
1)
0<
0Q
0>
0T
b1000000000000 9
13
b10101010101010101010101010101010 M
1S
1R
17
b10000000000 :
1=
#145000
0+
#148000
0)
#150000
1+
#152000
1)
0=
0S
03
1<
1T
1>
1Q
b10101010101010101010101000000000 L
b10101010101010101010101000000000 N
0R
07
#155000
0+
#156000
0)
#160000
1)
1+
0?
0T
0<
1S
0Q
b10101010101010101010101000000000 M
0>
#164000
0)
#165000
0+
#168000
1)
1Z
1F
b1110 Y
b111111111101 @
1W
1D
0S
1}
15
b1111111111 A
1J
b10101010101010101010101000000000 U
0/
#170000
1+
#172000
0)
#175000
0+
#176000
1)
05
1V
1E
0}
1C
0W
0D
1I
1K
0J
00
1X
#180000
0)
1+
#184000
1)
0X
1D
15
1W
0V
b1111 Y
0C
b1000000000000 @
1}
0E
b10101010101010101010101010101010 U
b10000000000 A
1J
0K
0I
#185000
0+
#188000
0)
#190000
1+
#192000
1)
1I
0}
1X
05
0D
1C
0W
1V
1K
1E
0J
#195000
0+
#196000
0)
#200000
1)
1+
1J
1W
0I
0C
1}
b1000000000100 @
1D
0X
15
b11 Y
0E
0V
0K
b10000000001 A
b1010101010101010 U
#204000
0)
#205000
0+
#208000
1)
05
0J
1X
1I
0W
0D
1C
0}
1K
1V
1E
#210000
1+
#212000
0)
#215000
0+
#216000
1)
0E
0F
0C
0Z
0X
0I
0V
0K
#220000
1+
0)
#224000
1)
1F
b0 U
1Z
1J
15
1W
1D
b1000000000001 @
b10 Y
1}
b10000000000 A
#225000
0+
#228000
0)
#230000
1+
#232000
1)
1K
0D
1X
1E
0W
05
1C
0J
0}
1V
1I
#235000
0+
#236000
0)
#240000
1)
1+
0I
0C
0K
0F
0X
0E
0Z
0V
#244000
0)
#245000
0+
#248000
1)
17
1?
1/
13
1=
1R
#250000
1+
#252000
0)
#255000
0+
#256000
1)
0R
b10101010101010100000000010101010 L
1>
1T
03
07
1<
1Q
0=
10
b10101010101010100000000010101010 N
#260000
0)
1+
#264000
1)
0<
0T
0>
b10101010101010100000000010101010 M
0?
1S
0Q
#265000
0+
#268000
0)
#270000
1+
#272000
1)
b1111111111 A
1D
0/
15
b10101010101010100000000000000000 U
1F
1W
0S
1J
1Z
1}
b1100 Y
b111111111110 @
#275000
0+
#276000
0)
#280000
1)
1+
1V
1I
1E
0D
1X
05
1K
1C
00
0W
0}
0J
#284000
0)
#285000
0+
#288000
1)
1J
b1000000000000 @
0K
0V
b10000000000 A
15
0I
b10101010101010101010101010101010 U
0X
1D
0E
1}
0C
b1111 Y
1W
#290000
1+
#292000
0)
#295000
0+
#296000
1)
0W
1K
0D
0J
1X
1V
1I
05
0}
1E
1C
#300000
1+
0)
#304000
1)
0C
0K
0I
1W
b1000000000100 @
0V
1D
b10000000001 A
0X
1J
b101010101010101010101010 U
0E
15
b111 Y
1}
#305000
0+
#308000
0)
#310000
1+
#312000
1)
0}
1I
0J
1K
1C
1X
0W
0D
1V
1E
05
#315000
0+
#316000
0)
#320000
1)
1+
0I
0F
0K
0X
0C
0E
0V
0Z
#324000
0)
#325000
0+
#328000
1)
1Z
1J
15
1}
1D
1W
b1000000000010 @
1F
b10000000000 A
b100 Y
b0 U
#330000
1+
#332000
0)
#335000
0+
#336000
1)
05
0J
1X
0}
1K
0W
0D
1I
1V
1E
1C
#340000
0)
1+
#344000
1)
0C
0F
0Z
0K
0X
0E
0V
0I
#345000
0+
#348000
0)
#350000
1+
#352000
1)
1R
b1000000000001 9
1?
13
1/
17
1=
#355000
0+
#356000
0)
#360000
1)
1+
0=
1Q
1>
b10101010000000001010101010101010 N
1T
0R
1<
b10101010000000001010101010101010 L
03
07
10
#364000
0)
#365000
0+
#368000
1)
0T
0Q
0>
0<
b10101010000000001010101010101010 M
0?
1S
#370000
1+
#372000
0)
#375000
0+
#376000
1)
0S
b10101010000000000000000000000000 U
0/
15
1D
1J
1Z
b111111111111 @
1F
1W
1}
b1000 Y
b1111111111 A
#380000
1+
0)
#384000
1)
1I
0W
1K
00
1C
0D
05
0J
0}
1V
1X
1E
#385000
0+
#388000
0)
#390000
1+
#392000
1)
0E
b10000000000 A
15
1W
0K
0I
b10101010101010101010101010101010 U
1D
0C
b1000000000000 @
0X
b1111 Y
0V
1}
1J
#395000
0+
#396000
0)
#400000
1)
1+
0J
1K
1C
0W
05
1E
0D
1I
0}
1V
1X
#404000
0)
#405000
0+
#408000
1)
0X
1W
1D
0C
0K
1J
b10000000001 A
0E
15
0V
b1000000000100 @
1}
0I
#410000
1+
#412000
0)
#415000
0+
#416000
1)
1I
1K
1E
1C
0D
0W
1X
0J
0}
05
1V
#420000
1+
0)
#424000
1)
0V
0X
0C
0E
0K
0I
0F
0Z
#425000
0+
#428000
0)
#430000
1+
#432000
1)
1Z
1D
1F
1W
b10000000000 A
b0 U
15
1J
1}
b1000000000011 @
b1000 Y
#435000
0+
#436000
0)
#440000
1)
1+
1C
1E
1X
1V
0W
1I
0D
1K
0}
0J
05
#444000
0)
#445000
0+
#448000
1)
0Z
0E
0C
0I
0X
0V
0F
0K
#450000
1+
#452000
0)
#455000
0+
#456000
1)
1/
1R
1=
b1000000000010 9
17
1?
13
#460000
0)
1+
#464000
1)
03
0=
b101010101010101010101010 L
1T
b101010101010101010101010 N
0R
1Q
10
1<
1>
07
#465000
0+
#468000
0)
#470000
1+
#472000
1)
17
0<
1=
b101010101010101010101010 M
13
1S
1R
0T
0Q
0>
b1000000000100 9
b10000000001 :
#475000
0+
#476000
0)
#480000
1)
1+
b10101010101010101010101010101010 L
1T
0=
1<
07
0R
03
b10101010101010101010101010101010 N
0S
1>
1Q
#484000
0)
#485000
0+
#488000
1)
0Q
b10101010101010101010101010101010 M
0T
0<
0>
1S
0?
#490000
1+
#492000
0)
#495000
0+
#496000
1)
15
0/
b1111111111 A
1Z
1D
b1111 Y
1W
0S
b10101010101010101010101010101010 U
1F
1J
1}
b111111111100 @
#500000
1+
0)
#504000
1)
1K
1V
05
0D
1E
00
1X
1I
1C
0}
0W
0J
#505000
0+
#508000
0)
#510000
1+
#512000
1)
1J
b1000000000000 @
0I
0K
b10000000000 A
0X
15
0V
1D
0E
1W
0C
1}
#515000
0+
#516000
0)
#520000
1)
1+
0}
1I
0D
0J
1V
1K
05
1X
1C
1E
0W
#524000
0)
#525000
0+
#528000
1)
1W
0I
15
1}
b1000000000100 @
b11 Y
0K
1D
b10000000001 A
0V
1J
0E
0X
0C
b1010101010101010 U
#530000
1+
#532000
0)
#535000
0+
#536000
1)
0}
1V
05
1I
0W
0D
1K
1C
0J
1X
1E
#540000
1+
0)
#544000
1)
0E
0Z
0V
0I
0X
0K
0C
0F
#545000
0+
#548000
0)
#550000
1+
#552000
1)
1F
b100000000 U
1D
1}
15
1Z
b1000000000000 @
1W
b10000000000 A
1J
#555000
0+
#556000
0)
#560000
1)
1+
0J
0D
1E
0W
1V
0}
05
1I
1C
1K
1X
#564000
0)
#565000
0+
#568000
1)
0X
0E
0F
0V
0Z
0K
0C
0I
#570000
1+
#572000
0)
#575000
0+
#576000
1)
1?
b1111111111 :
1=
1/
13
17
1R
b111111111111 9
#580000
1+
0)
#584000
1)
1Q
07
1T
03
0=
10
0R
1<
1>
#585000
0+
#588000
0)
#590000
1+
#592000
1)
0>
b1000000000000 9
b10000000000 :
1=
0Q
13
17
0T
0<
1S
1R
#595000
0+
#596000
0)
#600000
1)
1+
0R
07
1>
b10101010101010100000000100000000 N
b10101010101010100000000100000000 L
03
0=
1Q
0S
1T
1<
#604000
0)
#605000
0+
#608000
1)
0<
0>
0?
b10101010101010100000000100000000 M
0T
0Q
1S
#610000
1+
#612000
0)
#615000
0+
#616000
1)
0S
1}
1D
b10101010101010101010101000000000 U
1J
b111111111101 @
1F
b1110 Y
0/
1W
b1111111111 A
1Z
15
#620000
1+
0)
#624000
1)
05
0D
1I
1X
0}
1V
0J
1E
1C
00
0W
1K
#625000
0+
#628000
0)
#630000
1+
#632000
1)
0K
1J
0X
15
0I
1D
0V
b1111 Y
b10101010101010101010101010101010 U
1}
b1000000000000 @
1W
0E
0C
b10000000000 A
#635000
0+
#636000
0)
#640000
1)
1+
0}
05
1K
1X
0J
0D
1I
1V
1C
1E
0W
#644000
0)
#645000
0+
#648000
1)
1W
0I
0K
b10000000001 A
15
1}
1D
0X
b101010101010101010101010 U
1J
b111 Y
0E
b1000000000100 @
0C
0V
#650000
1+
#652000
0)
#655000
0+
#656000
1)
1V
0J
0W
1K
1I
0}
05
1X
0D
1C
1E
#660000
0)
1+
#664000
1)
0E
0X
0V
0K
0I
0F
0C
0Z
#665000
0+
#668000
0)
#670000
1+
#672000
1)
1Z
1W
b10000000000 A
1J
15
b10000000000000000 U
1}
1F
b110 Y
1D
b1000000000001 @
#675000
0+
#676000
0)
#680000
1)
1+
0W
1E
1I
05
1K
0J
1V
1X
0D
0}
1C
#684000
0)
#685000
0+
#688000
1)
0C
0V
0Z
0E
0K
0I
0X
0F
#690000
1+
#692000
0)
#695000
0+
#696000
1)
17
1?
1=
1/
1R
13
#700000
0)
1+
#704000
1)
03
1<
0R
0=
07
b10101010000000010000000010101010 N
1>
b10101010000000010000000010101010 L
1Q
10
1T
#705000
0+
#708000
0)
#710000
1+
#712000
1)
0T
0>
0<
1S
0?
b10101010000000010000000010101010 M
0Q
#715000
0+
#716000
0)
#720000
1)
1+
1W
b111111111110 @
b10101010101010100000000000000000 U
0S
1F
1J
0/
b1111111111 A
1Z
15
1}
1D
b1100 Y
#724000
0)
#725000
0+
#728000
1)
1K
0W
1C
1E
0J
1V
0D
05
00
1X
0}
1I
#730000
1+
#732000
0)
#735000
0+
#736000
1)
0I
b10101010101010101010101010101010 U
1J
b1000000000000 @
0K
b1111 Y
0E
0C
1W
b10000000000 A
1}
15
1D
0V
0X
#740000
1+
0)
#744000
1)
1X
0W
0J
1I
1C
1E
1K
1V
05
0}
0D
#745000
0+
#748000
0)
#750000
1+
#752000
1)
1D
b1000000000100 @
0E
0X
1W
0C
0I
1J
1}
0V
0K
b10000000001 A
15
#755000
0+
#756000
0)
